Workbook
Name Ativos: 'Saldo & Mov.'!$B$6:$B$8
Name Categorias: 'Despesas - Mapa'!$C$7:$C$15
Name Dash: 'Gráfico - Anual'!$A$1:$P$26
Name Despesas: 'Despesas - Mapa'!$C$7:$C$15
Name Investimentos: 'Receitas - Mapa'!$A$16:$A$17
Name Perdas: 'Receitas - Mapa'!$A$9:$A$12
Name Receitas: 'Receitas - Mapa'!$A$4:$A$6
Name Transferir: 'Saldo & Mov.'!$B$6:$B$8

Sheet Saldo & Mov.
B2: Mês | C2: Novembro
B3: Saldo | C3: =VLOOKUP(C2,'Gráfico - Anual'!A3:I14,9,FALSE) -> 100 | E3: Descrição | F3: Valor
B4: Despesas | C4: =SUM(F4:F14) -> 0 | E4: {=Categorias} -> Alimentação | F4: {=_xlfn._xlws.FILTER('Despesas - Mapa'!D7:AK15,'Despesas - Mapa'!D2:AK2=C2)} -> 0
E5: G. Resid. | F5: 0
B6: Banco 1 | C6: {=SUM(SUMIFS(Tabela1[Valor],Tabela1[Operação],{"Receitas";"Transferir"},Tabela1[Alocação],B6,Tabela1[Data],"<="&(TODAY())))-SUMIFS(Tabela1[Valor],Tabela1[Operação],"<>Receitas",Tabela1[Operação],"<>Transferir",Tabela1[Alocação],B6,Tabela1[Data],"<="&(TODAY())) - SUMIFS(Tabela1[Valor],Tabela1[Categoria],B6,Tabela1[Data],"<="&(TODAY()))} -> 100 | E6: Eletron e Jogos | F6: 0
B7: Banco 2 | C7: {=SUM(SUMIFS(Tabela1[Valor],Tabela1[Operação],{"Receitas";"Transferir"},Tabela1[Alocação],B7,Tabela1[Data],"<="&(TODAY())))-SUMIFS(Tabela1[Valor],Tabela1[Operação],"<>Receitas",Tabela1[Operação],"<>Transferir",Tabela1[Alocação],B7,Tabela1[Data],"<="&(TODAY())) - SUMIFS(Tabela1[Valor],Tabela1[Categoria],B7,Tabela1[Data],"<="&(TODAY()))} -> 0 | E7: Cursos | F7: 0
B8: Carteira | C8: {=SUM(SUMIFS(Tabela1[Valor],Tabela1[Operação],{"Receitas";"Transferir"},Tabela1[Alocação],B8,Tabela1[Data],"<="&(TODAY())))-SUMIFS(Tabela1[Valor],Tabela1[Operação],"<>Receitas",Tabela1[Operação],"<>Transferir",Tabela1[Alocação],B8,Tabela1[Data],"<="&(TODAY())) - SUMIFS(Tabela1[Valor],Tabela1[Categoria],B8,Tabela1[Data],"<="&(TODAY()))} -> 0 | E8: Farm. e Saúde. | F8: 0
B9: Sld. Real | C9: =SUM(C6:C8) -> 100 | E9: Entret e Livros | F9: 0
B10: Diferença | C10: =C3-C9 -> 0 | E10: Rolê | F10: 0
E11: Roupas | F11: 0
B12: Sld. Anual | C12: ='Gráfico - Anual'!I15 -> 100 | E12: G. Gerais | F12: 0
B14: =SUBTOTAL(2,Tabela1[Data]) -> 3
B15: Data | C15: Mês | D15: Operação | E15: Categoria | F15: Alocação | G15: Valor | H15: Descrição
B16: 45200 | C16: =IF(ISBLANK(B16),"",PROPER(TEXT(B16,"MMMM"))) -> Outubro | D16: Receitas | E16: Salário | F16: Banco 1 | G16: 150
B17: 45200 | C17: =IF(ISBLANK(B17),"",PROPER(TEXT(B17,"MMMM"))) -> Outubro | D17: Transferir | E17: Banco 1 | F17: Banco 2 | G17: 50
B18: 45201 | C18: =IF(ISBLANK(B18),"",PROPER(TEXT(B18,"MMMM"))) -> Outubro | D18: Investimentos | E18: CDB | F18: Banco 2 | G18: 50
C19: =IF(ISBLANK(B19),"",PROPER(TEXT(B19,"MMMM")))
C28: =IF(ISBLANK(B28),"",PROPER(TEXT(B28,"MMMM"))) | D28: =IF(ISBLANK(C28),"",PROPER(TEXT(C28,"MMMM"))) | E28: =IF(ISBLANK(D28),"",PROPER(TEXT(D28,"MMMM"))) | F28: =IF(ISBLANK(E28),"",PROPER(TEXT(E28,"MMMM"))) | G28: =IF(ISBLANK(F28),"",PROPER(TEXT(F28,"MMMM")))
C37: =IF(ISBLANK(B37),"",PROPER(TEXT(B37,"MMMM")))
C38: =IF(ISBLANK(B38),"",PROPER(TEXT(B38,"MMMM")))
C39: =IF(ISBLANK(B39),"",PROPER(TEXT(B39,"MMMM")))
C40: =IF(ISBLANK(B40),"",PROPER(TEXT(B40,"MMMM")))
C41: =IF(ISBLANK(B41),"",PROPER(TEXT(B41,"MMMM")))
C42: =IF(ISBLANK(B42),"",PROPER(TEXT(B42,"MMMM")))
C43: =IF(ISBLANK(B43),"",PROPER(TEXT(B43,"MMMM")))
C44: =IF(ISBLANK(B44),"",PROPER(TEXT(B44,"MMMM")))
C45: =IF(ISBLANK(B45),"",PROPER(TEXT(B45,"MMMM")))
C46: =IF(ISBLANK(B46),"",PROPER(TEXT(B46,"MMMM")))
C47: =IF(ISBLANK(B47),"",PROPER(TEXT(B47,"MMMM")))
C48: =IF(ISBLANK(B48),"",PROPER(TEXT(B48,"MMMM")))
... C555: =IF(ISBLANK(B555),"",PROPER(TEXT(B555,"MMMM")))

Sheet Receitas - Mapa
B2: =PROPER(TEXT("01/01","MMMM")) -> Janeiro | C2: =PROPER(TEXT("01/02","MMMM")) -> Fevereiro | D2: =PROPER(TEXT("01/03","MMMM")) -> Março | E2: =PROPER(TEXT("01/04","MMMM")) -> Abril | F2: =PROPER(TEXT("01/05","MMMM")) -> Maio | G2: =PROPER(TEXT("01/06","MMMM")) -> Junho | H2: =PROPER(TEXT("01/07","MMMM")) -> Julho | I2: =PROPER(TEXT("01/08","MMMM")) -> Agosto | J2: =PROPER(TEXT("01/09","MMMM")) -> Setembro | K2: =PROPER(TEXT("01/10","MMMM")) -> Outubro | L2: =PROPER(TEXT("01/11","MMMM")) -> Novembro | M2: =PROPER(TEXT("01/12","MMMM")) -> Dezembro
A3: Receitas
A4: Salário | B4: =SUMIFS(Tabela1[Valor],Tabela1[Mês],B$2,Tabela1[Categoria],$A4) -> 0 | C4: =SUMIFS(Tabela1[Valor],Tabela1[Mês],C$2,Tabela1[Categoria],$A4) -> 0 | D4: =SUMIFS(Tabela1[Valor],Tabela1[Mês],D$2,Tabela1[Categoria],$A4) -> 0 | E4: =SUMIFS(Tabela1[Valor],Tabela1[Mês],E$2,Tabela1[Categoria],$A4) -> 0 | F4: =SUMIFS(Tabela1[Valor],Tabela1[Mês],F$2,Tabela1[Categoria],$A4) -> 0 | G4: =SUMIFS(Tabela1[Valor],Tabela1[Mês],G$2,Tabela1[Categoria],$A4) -> 0 | H4: =SUMIFS(Tabela1[Valor],Tabela1[Mês],H$2,Tabela1[Categoria],$A4) -> 0 | I4: =SUMIFS(Tabela1[Valor],Tabela1[Mês],I$2,Tabela1[Categoria],$A4) -> 0 | ... M4: =SUMIFS(Tabela1[Valor],Tabela1[Mês],M$2,Tabela1[Categoria],$A4) -> 0
A5: Vendas | B5: =SUMIFS(Tabela1[Valor],Tabela1[Mês],B$2,Tabela1[Categoria],$A5) -> 0 | C5: =SUMIFS(Tabela1[Valor],Tabela1[Mês],C$2,Tabela1[Categoria],$A5) -> 0 | D5: =SUMIFS(Tabela1[Valor],Tabela1[Mês],D$2,Tabela1[Categoria],$A5) -> 0 | E5: =SUMIFS(Tabela1[Valor],Tabela1[Mês],E$2,Tabela1[Categoria],$A5) -> 0 | F5: =SUMIFS(Tabela1[Valor],Tabela1[Mês],F$2,Tabela1[Categoria],$A5) -> 0 | G5: =SUMIFS(Tabela1[Valor],Tabela1[Mês],G$2,Tabela1[Categoria],$A5) -> 0 | H5: =SUMIFS(Tabela1[Valor],Tabela1[Mês],H$2,Tabela1[Categoria],$A5) -> 0 | I5: =SUMIFS(Tabela1[Valor],Tabela1[Mês],I$2,Tabela1[Categoria],$A5) -> 0 | ... M5: =SUMIFS(Tabela1[Valor],Tabela1[Mês],M$2,Tabela1[Categoria],$A5) -> 0
A6: Outros | B6: =SUMIFS(Tabela1[Valor],Tabela1[Mês],B$2,Tabela1[Categoria],$A6) -> 0 | C6: =SUMIFS(Tabela1[Valor],Tabela1[Mês],C$2,Tabela1[Categoria],$A6) -> 0 | D6: =SUMIFS(Tabela1[Valor],Tabela1[Mês],D$2,Tabela1[Categoria],$A6) -> 0 | E6: =SUMIFS(Tabela1[Valor],Tabela1[Mês],E$2,Tabela1[Categoria],$A6) -> 0 | F6: =SUMIFS(Tabela1[Valor],Tabela1[Mês],F$2,Tabela1[Categoria],$A6) -> 0 | G6: =SUMIFS(Tabela1[Valor],Tabela1[Mês],G$2,Tabela1[Categoria],$A6) -> 0 | H6: =SUMIFS(Tabela1[Valor],Tabela1[Mês],H$2,Tabela1[Categoria],$A6) -> 0 | I6: =SUMIFS(Tabela1[Valor],Tabela1[Mês],I$2,Tabela1[Categoria],$A6) -> 0 | ... M6: =SUMIFS(Tabela1[Valor],Tabela1[Mês],M$2,Tabela1[Categoria],$A6) -> 0
A8: Perdas
A9: Inss | B9: =SUMIFS(Tabela1[Valor],Tabela1[Mês],B$2,Tabela1[Categoria],$A9) -> 0 | C9: =SUMIFS(Tabela1[Valor],Tabela1[Mês],C$2,Tabela1[Categoria],$A9) -> 0 | D9: =SUMIFS(Tabela1[Valor],Tabela1[Mês],D$2,Tabela1[Categoria],$A9) -> 0 | E9: =SUMIFS(Tabela1[Valor],Tabela1[Mês],E$2,Tabela1[Categoria],$A9) -> 0 | F9: =SUMIFS(Tabela1[Valor],Tabela1[Mês],F$2,Tabela1[Categoria],$A9) -> 0 | G9: =SUMIFS(Tabela1[Valor],Tabela1[Mês],G$2,Tabela1[Categoria],$A9) -> 0 | H9: =SUMIFS(Tabela1[Valor],Tabela1[Mês],H$2,Tabela1[Categoria],$A9) -> 0 | I9: =SUMIFS(Tabela1[Valor],Tabela1[Mês],I$2,Tabela1[Categoria],$A9) -> 0 | ... M9: =SUMIFS(Tabela1[Valor],Tabela1[Mês],M$2,Tabela1[Categoria],$A9) -> 0
A10: T. Trans. | B10: =SUMIFS(Tabela1[Valor],Tabela1[Mês],B$2,Tabela1[Categoria],$A10) -> 0 | C10: =SUMIFS(Tabela1[Valor],Tabela1[Mês],C$2,Tabela1[Categoria],$A10) -> 0 | D10: =SUMIFS(Tabela1[Valor],Tabela1[Mês],D$2,Tabela1[Categoria],$A10) -> 0 | E10: =SUMIFS(Tabela1[Valor],Tabela1[Mês],E$2,Tabela1[Categoria],$A10) -> 0 | F10: =SUMIFS(Tabela1[Valor],Tabela1[Mês],F$2,Tabela1[Categoria],$A10) -> 0 | G10: =SUMIFS(Tabela1[Valor],Tabela1[Mês],G$2,Tabela1[Categoria],$A10) -> 0 | H10: =SUMIFS(Tabela1[Valor],Tabela1[Mês],H$2,Tabela1[Categoria],$A10) -> 0 | I10: =SUMIFS(Tabela1[Valor],Tabela1[Mês],I$2,Tabela1[Categoria],$A10) -> 0 | ... M10: =SUMIFS(Tabela1[Valor],Tabela1[Mês],M$2,Tabela1[Categoria],$A10) -> 0
A11: Perdas Outros | B11: =SUMIFS(Tabela1[Valor],Tabela1[Mês],B$2,Tabela1[Categoria],$A11) -> 0 | C11: =SUMIFS(Tabela1[Valor],Tabela1[Mês],C$2,Tabela1[Categoria],$A11) -> 0 | D11: =SUMIFS(Tabela1[Valor],Tabela1[Mês],D$2,Tabela1[Categoria],$A11) -> 0 | E11: =SUMIFS(Tabela1[Valor],Tabela1[Mês],E$2,Tabela1[Categoria],$A11) -> 0 | F11: =SUMIFS(Tabela1[Valor],Tabela1[Mês],F$2,Tabela1[Categoria],$A11) -> 0 | G11: =SUMIFS(Tabela1[Valor],Tabela1[Mês],G$2,Tabela1[Categoria],$A11) -> 0 | H11: =SUMIFS(Tabela1[Valor],Tabela1[Mês],H$2,Tabela1[Categoria],$A11) -> 0 | I11: =SUMIFS(Tabela1[Valor],Tabela1[Mês],I$2,Tabela1[Categoria],$A11) -> 0 | ... M11: =SUMIFS(Tabela1[Valor],Tabela1[Mês],M$2,Tabela1[Categoria],$A11) -> 0
A12: Dízimo | B12: =SUMIFS(Tabela1[Valor],Tabela1[Mês],B$2,Tabela1[Categoria],$A12) -> 0 | C12: =SUMIFS(Tabela1[Valor],Tabela1[Mês],C$2,Tabela1[Categoria],$A12) -> 0 | D12: =SUMIFS(Tabela1[Valor],Tabela1[Mês],D$2,Tabela1[Categoria],$A12) -> 0 | E12: =SUMIFS(Tabela1[Valor],Tabela1[Mês],E$2,Tabela1[Categoria],$A12) -> 0 | F12: =SUMIFS(Tabela1[Valor],Tabela1[Mês],F$2,Tabela1[Categoria],$A12) -> 0 | G12: =SUMIFS(Tabela1[Valor],Tabela1[Mês],G$2,Tabela1[Categoria],$A12) -> 0 | H12: =SUMIFS(Tabela1[Valor],Tabela1[Mês],H$2,Tabela1[Categoria],$A12) -> 0 | I12: =SUMIFS(Tabela1[Valor],Tabela1[Mês],I$2,Tabela1[Categoria],$A12) -> 0 | ... M12: =SUMIFS(Tabela1[Valor],Tabela1[Mês],M$2,Tabela1[Categoria],$A12) -> 0
A13: Cont. Dízimo | B13: =IF((SUM(B4:B6)-SUM(B9:B11)) > 10, ((SUM(B4:B6)-SUM(B9:B11))*0.1), (0))-B12 -> 0 | C13: =IF((SUM(C4:C6)-SUM(C9:C11)) > 10, ((SUM(C4:C6)-SUM(C9:C11))*0.1), (0))-C12 -> 0 | D13: =IF((SUM(D4:D6)-SUM(D9:D11)) > 10, ((SUM(D4:D6)-SUM(D9:D11))*0.1), (0))-D12 -> 0 | E13: =IF((SUM(E4:E6)-SUM(E9:E11)) > 10, ((SUM(E4:E6)-SUM(E9:E11))*0.1), (0))-E12 -> 0 | F13: =IF((SUM(F4:F6)-SUM(F9:F11)) > 10, ((SUM(F4:F6)-SUM(F9:F11))*0.1), (0))-F12 -> 0 | G13: =IF((SUM(G4:G6)-SUM(G9:G11)) > 10, ((SUM(G4:G6)-SUM(G9:G11))*0.1), (0))-G12 -> 0 | H13: =IF((SUM(H4:H6)-SUM(H9:H11)) > 10, ((SUM(H4:H6)-SUM(H9:H11))*0.1), (0))-H12 -> 0 | I13: =IF((SUM(I4:I6)-SUM(I9:I11)) > 10, ((SUM(I4:I6)-SUM(I9:I11))*0.1), (0))-I12 -> 0 | ... M13: =IF((SUM(M4:M6)-SUM(M9:M11)) > 10, ((SUM(M4:M6)-SUM(M9:M11))*0.1), (0))-M12 -> 0
A15: Investimentos
A16: CDB | B16: =SUMIFS(Tabela1[Valor],Tabela1[Mês],B$2,Tabela1[Categoria],$A16) -> 0 | C16: =SUMIFS(Tabela1[Valor],Tabela1[Mês],C$2,Tabela1[Categoria],$A16) -> 0 | D16: =SUMIFS(Tabela1[Valor],Tabela1[Mês],D$2,Tabela1[Categoria],$A16) -> 0 | E16: =SUMIFS(Tabela1[Valor],Tabela1[Mês],E$2,Tabela1[Categoria],$A16) -> 0 | F16: =SUMIFS(Tabela1[Valor],Tabela1[Mês],F$2,Tabela1[Categoria],$A16) -> 0 | G16: =SUMIFS(Tabela1[Valor],Tabela1[Mês],G$2,Tabela1[Categoria],$A16) -> 0 | H16: =SUMIFS(Tabela1[Valor],Tabela1[Mês],H$2,Tabela1[Categoria],$A16) -> 0 | I16: =SUMIFS(Tabela1[Valor],Tabela1[Mês],I$2,Tabela1[Categoria],$A16) -> 0 | ... M16: =SUMIFS(Tabela1[Valor],Tabela1[Mês],M$2,Tabela1[Categoria],$A16) -> 0
A17: CDI | B17: =SUMIFS(Tabela1[Valor],Tabela1[Mês],B$2,Tabela1[Categoria],$A17) -> 0 | C17: =SUMIFS(Tabela1[Valor],Tabela1[Mês],C$2,Tabela1[Categoria],$A17) -> 0 | D17: =SUMIFS(Tabela1[Valor],Tabela1[Mês],D$2,Tabela1[Categoria],$A17) -> 0 | E17: =SUMIFS(Tabela1[Valor],Tabela1[Mês],E$2,Tabela1[Categoria],$A17) -> 0 | F17: =SUMIFS(Tabela1[Valor],Tabela1[Mês],F$2,Tabela1[Categoria],$A17) -> 0 | G17: =SUMIFS(Tabela1[Valor],Tabela1[Mês],G$2,Tabela1[Categoria],$A17) -> 0 | H17: =SUMIFS(Tabela1[Valor],Tabela1[Mês],H$2,Tabela1[Categoria],$A17) -> 0 | I17: =SUMIFS(Tabela1[Valor],Tabela1[Mês],I$2,Tabela1[Categoria],$A17) -> 0 | ... M17: =SUMIFS(Tabela1[Valor],Tabela1[Mês],M$2,Tabela1[Categoria],$A17) -> 0
A19: Total Geral | B19: =ROUND(SUM(B4:B6)-SUM(B16:B17)-SUM(B9:B12),2) -> 0 | C19: =ROUND(SUM(C4:C6)-SUM(C16:C17)-SUM(C9:C12),2) -> 0 | D19: =ROUND(SUM(D4:D6)-SUM(D16:D17)-SUM(D9:D12),2) -> 0 | E19: =ROUND(SUM(E4:E6)-SUM(E16:E17)-SUM(E9:E12),2) -> 0 | F19: =ROUND(SUM(F4:F6)-SUM(F16:F17)-SUM(F9:F12),2) -> 0 | G19: =ROUND(SUM(G4:G6)-SUM(G16:G17)-SUM(G9:G12),2) -> 0 | H19: =ROUND(SUM(H4:H6)-SUM(H16:H17)-SUM(H9:H12),2) -> 0 | I19: =ROUND(SUM(I4:I6)-SUM(I16:I17)-SUM(I9:I12),2) -> 0 | ... M19: =ROUND(SUM(M4:M6)-SUM(M16:M17)-SUM(M9:M12),2) -> 0

Sheet Despesas - Mapa
A2: Mês | D2: =PROPER(TEXT("01/01","MMMM")) -> Janeiro | G2: =PROPER(TEXT("1/02","MMMM")) -> Fevereiro | J2: =PROPER(TEXT("1/03","MMMM")) -> Março | M2: =PROPER(TEXT("1/04","MMMM")) -> Abril | P2: =PROPER(TEXT("1/05","MMMM")) -> Maio | S2: =PROPER(TEXT("1/06","MMMM")) -> Junho | V2: =PROPER(TEXT("1/07","MMMM")) -> Julho | Y2: =PROPER(TEXT("1/08","MMMM")) -> Agosto | AB2: =PROPER(TEXT("1/09","MMMM")) -> Setembro | AE2: =PROPER(TEXT("1/10","MMMM")) -> Outubro | AH2: =PROPER(TEXT("1/11","MMMM")) -> Novembro | AK2: =PROPER(TEXT("1/12","MMMM")) -> Dezembro
A3: Receitas L. | D3: ='Receitas - Mapa'!B19 -> 0 | G3: ='Receitas - Mapa'!C19 -> 0 | J3: ='Receitas - Mapa'!D19 -> 0 | M3: ='Receitas - Mapa'!E19 -> 0 | P3: ='Receitas - Mapa'!F19 -> 0 | S3: ='Receitas - Mapa'!G19 -> 0 | V3: ='Receitas - Mapa'!H19 -> 0 | Y3: ='Receitas - Mapa'!I19 -> 0 | AB3: ='Receitas - Mapa'!J19 -> 0 | AE3: ='Receitas - Mapa'!K19 -> 100 | AH3: ='Receitas - Mapa'!L19 -> 0 | AK3: ='Receitas - Mapa'!M19 -> 0
A4: Saldo | D4: =D3-(SUM(D7:D15)) -> 0 | G4: =G3-(SUM(G7:G15))+D4 -> 0 | J4: =J3-(SUM(J7:J15))+G4 -> 0 | M4: =M3-(SUM(M7:M15))+J4 -> 0 | P4: =P3-(SUM(P7:P15))+M4 -> 0 | S4: =S3-(SUM(S7:S15))+P4 -> 0 | V4: =V3-(SUM(V7:V15))+S4 -> 0 | Y4: =Y3-(SUM(Y7:Y15))+V4 -> 0 | AB4: =AB3-(SUM(AB7:AB15))+Y4 -> 0 | AE4: =AE3-(SUM(AE7:AE15))+AB4 -> 100 | AH4: =AH3-(SUM(AH7:AH15))+AE4 -> 100 | AK4: =AK3-SUM(AK7:AK15)+AH4 -> 100
A6: Despesas Fixas | C6: Descrição | D6: Valor | F6: Descrição | G6: Valor | I6: Descrição | J6: Valor | L6: Descrição | M6: Valor | O6: Descrição | P6: Valor | R6: Descrição | S6: Valor | U6: Descrição | V6: Valor | X6: Descrição | Y6: Valor | AA6: Descrição | AB6: Valor | AD6: Descrição | AE6: Valor | AG6: Descrição | AH6: Valor | AJ6: Descrição | AK6: Valor
C7: Alimentação | D7: =SUMIFS(Tabela1[Valor],Tabela1[Mês],'Despesas - Mapa'!D$2,Tabela1[Categoria],'Despesas - Mapa'!C7) -> 0 | F7: {=Categorias} -> Alimentação | G7: =SUMIFS(Tabela1[Valor],Tabela1[Mês],'Despesas - Mapa'!G$2,Tabela1[Categoria],'Despesas - Mapa'!F7) -> 0 | I7: {=Categorias} -> Alimentação | J7: =SUMIFS(Tabela1[Valor],Tabela1[Mês],'Despesas - Mapa'!J$2,Tabela1[Categoria],'Despesas - Mapa'!I7) -> 0 | L7: {=Categorias} -> Alimentação | M7: =SUMIFS(Tabela1[Valor],Tabela1[Mês],'Despesas - Mapa'!M$2,Tabela1[Categoria],'Despesas - Mapa'!L7) -> 0 | O7: {=Categorias} -> Alimentação | P7: =SUMIFS(Tabela1[Valor],Tabela1[Mês],'Despesas - Mapa'!P$2,Tabela1[Categoria],'Despesas - Mapa'!O7) -> 0 | R7: {=Categorias} -> Alimentação | S7: =SUMIFS(Tabela1[Valor],Tabela1[Mês],'Despesas - Mapa'!S$2,Tabela1[Categoria],'Despesas - Mapa'!R7) -> 0 | U7: {=Categorias} -> Alimentação | V7: =SUMIFS(Tabela1[Valor],Tabela1[Mês],'Despesas - Mapa'!V$2,Tabela1[Categoria],'Despesas - Mapa'!U7) -> 0 | X7: {=Categorias} -> Alimentação | Y7: =SUMIFS(Tabela1[Valor],Tabela1[Mês],'Despesas - Mapa'!Y$2,Tabela1[Categoria],'Despesas - Mapa'!X7) -> 0 | AA7: {=Categorias} -> Alimentação | AB7: =SUMIFS(Tabela1[Valor],Tabela1[Mês],'Despesas - Mapa'!AB$2,Tabela1[Categoria],'Despesas - Mapa'!AA7) -> 0 | AD7: {=Categorias} -> Alimentação | AE7: =SUMIFS(Tabela1[Valor],Tabela1[Mês],'Despesas - Mapa'!AE$2,Tabela1[Categoria],'Despesas - Mapa'!AD7) -> 0 | AG7: {=Categorias} -> Alimentação | AH7: =SUMIFS(Tabela1[Valor],Tabela1[Mês],'Despesas - Mapa'!AH$2,Tabela1[Categoria],'Despesas - Mapa'!AG7) -> 0 | AJ7: {=Categorias} -> Alimentação | AK7: =SUMIFS(Tabela1[Valor],Tabela1[Mês],'Despesas - Mapa'!AK$2,Tabela1[Categoria],'Despesas - Mapa'!AJ7) -> 0
C8: G. Resid. | D8: =SUMIFS(Tabela1[Valor],Tabela1[Mês],'Despesas - Mapa'!D$2,Tabela1[Categoria],'Despesas - Mapa'!C8) -> 0 | F8: G. Resid. | G8: =SUMIFS(Tabela1[Valor],Tabela1[Mês],'Despesas - Mapa'!G$2,Tabela1[Categoria],'Despesas - Mapa'!F8) -> 0 | I8: G. Resid. | J8: =SUMIFS(Tabela1[Valor],Tabela1[Mês],'Despesas - Mapa'!J$2,Tabela1[Categoria],'Despesas - Mapa'!I8) -> 0 | L8: G. Resid. | M8: =SUMIFS(Tabela1[Valor],Tabela1[Mês],'Despesas - Mapa'!M$2,Tabela1[Categoria],'Despesas - Mapa'!L8) -> 0 | O8: G. Resid. | P8: =SUMIFS(Tabela1[Valor],Tabela1[Mês],'Despesas - Mapa'!P$2,Tabela1[Categoria],'Despesas - Mapa'!O8) -> 0 | R8: G. Resid. | S8: =SUMIFS(Tabela1[Valor],Tabela1[Mês],'Despesas - Mapa'!S$2,Tabela1[Categoria],'Despesas - Mapa'!R8) -> 0 | U8: G. Resid. | V8: =SUMIFS(Tabela1[Valor],Tabela1[Mês],'Despesas - Mapa'!V$2,Tabela1[Categoria],'Despesas - Mapa'!U8) -> 0 | X8: G. Resid. | Y8: =SUMIFS(Tabela1[Valor],Tabela1[Mês],'Despesas - Mapa'!Y$2,Tabela1[Categoria],'Despesas - Mapa'!X8) -> 0 | AA8: G. Resid. | AB8: =SUMIFS(Tabela1[Valor],Tabela1[Mês],'Despesas - Mapa'!AB$2,Tabela1[Categoria],'Despesas - Mapa'!AA8) -> 0 | AD8: G. Resid. | AE8: =SUMIFS(Tabela1[Valor],Tabela1[Mês],'Despesas - Mapa'!AE$2,Tabela1[Categoria],'Despesas - Mapa'!AD8) -> 0 | AG8: G. Resid. | AH8: =SUMIFS(Tabela1[Valor],Tabela1[Mês],'Despesas - Mapa'!AH$2,Tabela1[Categoria],'Despesas - Mapa'!AG8) -> 0 | AJ8: G. Resid. | AK8: =SUMIFS(Tabela1[Valor],Tabela1[Mês],'Despesas - Mapa'!AK$2,Tabela1[Categoria],'Despesas - Mapa'!AJ8) -> 0
C9: Eletron e Jogos | D9: =SUMIFS(Tabela1[Valor],Tabela1[Mês],'Despesas - Mapa'!D$2,Tabela1[Categoria],'Despesas - Mapa'!C9) -> 0 | F9: Eletron e Jogos | G9: =SUMIFS(Tabela1[Valor],Tabela1[Mês],'Despesas - Mapa'!G$2,Tabela1[Categoria],'Despesas - Mapa'!F9) -> 0 | I9: Eletron e Jogos | J9: =SUMIFS(Tabela1[Valor],Tabela1[Mês],'Despesas - Mapa'!J$2,Tabela1[Categoria],'Despesas - Mapa'!I9) -> 0 | L9: Eletron e Jogos | M9: =SUMIFS(Tabela1[Valor],Tabela1[Mês],'Despesas - Mapa'!M$2,Tabela1[Categoria],'Despesas - Mapa'!L9) -> 0 | O9: Eletron e Jogos | P9: =SUMIFS(Tabela1[Valor],Tabela1[Mês],'Despesas - Mapa'!P$2,Tabela1[Categoria],'Despesas - Mapa'!O9) -> 0 | R9: Eletron e Jogos | S9: =SUMIFS(Tabela1[Valor],Tabela1[Mês],'Despesas - Mapa'!S$2,Tabela1[Categoria],'Despesas - Mapa'!R9) -> 0 | U9: Eletron e Jogos | V9: =SUMIFS(Tabela1[Valor],Tabela1[Mês],'Despesas - Mapa'!V$2,Tabela1[Categoria],'Despesas - Mapa'!U9) -> 0 | X9: Eletron e Jogos | Y9: =SUMIFS(Tabela1[Valor],Tabela1[Mês],'Despesas - Mapa'!Y$2,Tabela1[Categoria],'Despesas - Mapa'!X9) -> 0 | AA9: Eletron e Jogos | AB9: =SUMIFS(Tabela1[Valor],Tabela1[Mês],'Despesas - Mapa'!AB$2,Tabela1[Categoria],'Despesas - Mapa'!AA9) -> 0 | AD9: Eletron e Jogos | AE9: =SUMIFS(Tabela1[Valor],Tabela1[Mês],'Despesas - Mapa'!AE$2,Tabela1[Categoria],'Despesas - Mapa'!AD9) -> 0 | AG9: Eletron e Jogos | AH9: =SUMIFS(Tabela1[Valor],Tabela1[Mês],'Despesas - Mapa'!AH$2,Tabela1[Categoria],'Despesas - Mapa'!AG9) -> 0 | AJ9: Eletron e Jogos | AK9: =SUMIFS(Tabela1[Valor],Tabela1[Mês],'Despesas - Mapa'!AK$2,Tabela1[Categoria],'Despesas - Mapa'!AJ9) -> 0
C10: Cursos | D10: =SUMIFS(Tabela1[Valor],Tabela1[Mês],'Despesas - Mapa'!D$2,Tabela1[Categoria],'Despesas - Mapa'!C10) -> 0 | F10: Cursos | G10: =SUMIFS(Tabela1[Valor],Tabela1[Mês],'Despesas - Mapa'!G$2,Tabela1[Categoria],'Despesas - Mapa'!F10) -> 0 | I10: Cursos | J10: =SUMIFS(Tabela1[Valor],Tabela1[Mês],'Despesas - Mapa'!J$2,Tabela1[Categoria],'Despesas - Mapa'!I10) -> 0 | L10: Cursos | M10: =SUMIFS(Tabela1[Valor],Tabela1[Mês],'Despesas - Mapa'!M$2,Tabela1[Categoria],'Despesas - Mapa'!L10) -> 0 | O10: Cursos | P10: =SUMIFS(Tabela1[Valor],Tabela1[Mês],'Despesas - Mapa'!P$2,Tabela1[Categoria],'Despesas - Mapa'!O10) -> 0 | R10: Cursos | S10: =SUMIFS(Tabela1[Valor],Tabela1[Mês],'Despesas - Mapa'!S$2,Tabela1[Categoria],'Despesas - Mapa'!R10) -> 0 | U10: Cursos | V10: =SUMIFS(Tabela1[Valor],Tabela1[Mês],'Despesas - Mapa'!V$2,Tabela1[Categoria],'Despesas - Mapa'!U10) -> 0 | X10: Cursos | Y10: =SUMIFS(Tabela1[Valor],Tabela1[Mês],'Despesas - Mapa'!Y$2,Tabela1[Categoria],'Despesas - Mapa'!X10) -> 0 | AA10: Cursos | AB10: =SUMIFS(Tabela1[Valor],Tabela1[Mês],'Despesas - Mapa'!AB$2,Tabela1[Categoria],'Despesas - Mapa'!AA10) -> 0 | AD10: Cursos | AE10: =SUMIFS(Tabela1[Valor],Tabela1[Mês],'Despesas - Mapa'!AE$2,Tabela1[Categoria],'Despesas - Mapa'!AD10) -> 0 | AG10: Cursos | AH10: =SUMIFS(Tabela1[Valor],Tabela1[Mês],'Despesas - Mapa'!AH$2,Tabela1[Categoria],'Despesas - Mapa'!AG10) -> 0 | AJ10: Cursos | AK10: =SUMIFS(Tabela1[Valor],Tabela1[Mês],'Despesas - Mapa'!AK$2,Tabela1[Categoria],'Despesas - Mapa'!AJ10) -> 0
C11: Farm. e Saúde. | D11: =SUMIFS(Tabela1[Valor],Tabela1[Mês],'Despesas - Mapa'!D$2,Tabela1[Categoria],'Despesas - Mapa'!C11) -> 0 | F11: Farm. e Saúde. | G11: =SUMIFS(Tabela1[Valor],Tabela1[Mês],'Despesas - Mapa'!G$2,Tabela1[Categoria],'Despesas - Mapa'!F11) -> 0 | I11: Farm. e Saúde. | J11: =SUMIFS(Tabela1[Valor],Tabela1[Mês],'Despesas - Mapa'!J$2,Tabela1[Categoria],'Despesas - Mapa'!I11) -> 0 | L11: Farm. e Saúde. | M11: =SUMIFS(Tabela1[Valor],Tabela1[Mês],'Despesas - Mapa'!M$2,Tabela1[Categoria],'Despesas - Mapa'!L11) -> 0 | O11: Farm. e Saúde. | P11: =SUMIFS(Tabela1[Valor],Tabela1[Mês],'Despesas - Mapa'!P$2,Tabela1[Categoria],'Despesas - Mapa'!O11) -> 0 | R11: Farm. e Saúde. | S11: =SUMIFS(Tabela1[Valor],Tabela1[Mês],'Despesas - Mapa'!S$2,Tabela1[Categoria],'Despesas - Mapa'!R11) -> 0 | U11: Farm. e Saúde. | V11: =SUMIFS(Tabela1[Valor],Tabela1[Mês],'Despesas - Mapa'!V$2,Tabela1[Categoria],'Despesas - Mapa'!U11) -> 0 | X11: Farm. e Saúde. | Y11: =SUMIFS(Tabela1[Valor],Tabela1[Mês],'Despesas - Mapa'!Y$2,Tabela1[Categoria],'Despesas - Mapa'!X11) -> 0 | AA11: Farm. e Saúde. | AB11: =SUMIFS(Tabela1[Valor],Tabela1[Mês],'Despesas - Mapa'!AB$2,Tabela1[Categoria],'Despesas - Mapa'!AA11) -> 0 | AD11: Farm. e Saúde. | AE11: =SUMIFS(Tabela1[Valor],Tabela1[Mês],'Despesas - Mapa'!AE$2,Tabela1[Categoria],'Despesas - Mapa'!AD11) -> 0 | AG11: Farm. e Saúde. | AH11: =SUMIFS(Tabela1[Valor],Tabela1[Mês],'Despesas - Mapa'!AH$2,Tabela1[Categoria],'Despesas - Mapa'!AG11) -> 0 | AJ11: Farm. e Saúde. | AK11: =SUMIFS(Tabela1[Valor],Tabela1[Mês],'Despesas - Mapa'!AK$2,Tabela1[Categoria],'Despesas - Mapa'!AJ11) -> 0
C12: Entret e Livros | D12: =SUMIFS(Tabela1[Valor],Tabela1[Mês],'Despesas - Mapa'!D$2,Tabela1[Categoria],'Despesas - Mapa'!C12) -> 0 | F12: Entret e Livros | G12: =SUMIFS(Tabela1[Valor],Tabela1[Mês],'Despesas - Mapa'!G$2,Tabela1[Categoria],'Despesas - Mapa'!F12) -> 0 | I12: Entret e Livros | J12: =SUMIFS(Tabela1[Valor],Tabela1[Mês],'Despesas - Mapa'!J$2,Tabela1[Categoria],'Despesas - Mapa'!I12) -> 0 | L12: Entret e Livros | M12: =SUMIFS(Tabela1[Valor],Tabela1[Mês],'Despesas - Mapa'!M$2,Tabela1[Categoria],'Despesas - Mapa'!L12) -> 0 | O12: Entret e Livros | P12: =SUMIFS(Tabela1[Valor],Tabela1[Mês],'Despesas - Mapa'!P$2,Tabela1[Categoria],'Despesas - Mapa'!O12) -> 0 | R12: Entret e Livros | S12: =SUMIFS(Tabela1[Valor],Tabela1[Mês],'Despesas - Mapa'!S$2,Tabela1[Categoria],'Despesas - Mapa'!R12) -> 0 | U12: Entret e Livros | V12: =SUMIFS(Tabela1[Valor],Tabela1[Mês],'Despesas - Mapa'!V$2,Tabela1[Categoria],'Despesas - Mapa'!U12) -> 0 | X12: Entret e Livros | Y12: =SUMIFS(Tabela1[Valor],Tabela1[Mês],'Despesas - Mapa'!Y$2,Tabela1[Categoria],'Despesas - Mapa'!X12) -> 0 | AA12: Entret e Livros | AB12: =SUMIFS(Tabela1[Valor],Tabela1[Mês],'Despesas - Mapa'!AB$2,Tabela1[Categoria],'Despesas - Mapa'!AA12) -> 0 | AD12: Entret e Livros | AE12: =SUMIFS(Tabela1[Valor],Tabela1[Mês],'Despesas - Mapa'!AE$2,Tabela1[Categoria],'Despesas - Mapa'!AD12) -> 0 | AG12: Entret e Livros | AH12: =SUMIFS(Tabela1[Valor],Tabela1[Mês],'Despesas - Mapa'!AH$2,Tabela1[Categoria],'Despesas - Mapa'!AG12) -> 0 | AJ12: Entret e Livros | AK12: =SUMIFS(Tabela1[Valor],Tabela1[Mês],'Despesas - Mapa'!AK$2,Tabela1[Categoria],'Despesas - Mapa'!AJ12) -> 0
C13: Rolê | D13: =SUMIFS(Tabela1[Valor],Tabela1[Mês],'Despesas - Mapa'!D$2,Tabela1[Categoria],'Despesas - Mapa'!C13) -> 0 | F13: Rolê | G13: =SUMIFS(Tabela1[Valor],Tabela1[Mês],'Despesas - Mapa'!G$2,Tabela1[Categoria],'Despesas - Mapa'!F13) -> 0 | I13: Rolê | J13: =SUMIFS(Tabela1[Valor],Tabela1[Mês],'Despesas - Mapa'!J$2,Tabela1[Categoria],'Despesas - Mapa'!I13) -> 0 | L13: Rolê | M13: =SUMIFS(Tabela1[Valor],Tabela1[Mês],'Despesas - Mapa'!M$2,Tabela1[Categoria],'Despesas - Mapa'!L13) -> 0 | O13: Rolê | P13: =SUMIFS(Tabela1[Valor],Tabela1[Mês],'Despesas - Mapa'!P$2,Tabela1[Categoria],'Despesas - Mapa'!O13) -> 0 | R13: Rolê | S13: =SUMIFS(Tabela1[Valor],Tabela1[Mês],'Despesas - Mapa'!S$2,Tabela1[Categoria],'Despesas - Mapa'!R13) -> 0 | U13: Rolê | V13: =SUMIFS(Tabela1[Valor],Tabela1[Mês],'Despesas - Mapa'!V$2,Tabela1[Categoria],'Despesas - Mapa'!U13) -> 0 | X13: Rolê | Y13: =SUMIFS(Tabela1[Valor],Tabela1[Mês],'Despesas - Mapa'!Y$2,Tabela1[Categoria],'Despesas - Mapa'!X13) -> 0 | AA13: Rolê | AB13: =SUMIFS(Tabela1[Valor],Tabela1[Mês],'Despesas - Mapa'!AB$2,Tabela1[Categoria],'Despesas - Mapa'!AA13) -> 0 | AD13: Rolê | AE13: =SUMIFS(Tabela1[Valor],Tabela1[Mês],'Despesas - Mapa'!AE$2,Tabela1[Categoria],'Despesas - Mapa'!AD13) -> 0 | AG13: Rolê | AH13: =SUMIFS(Tabela1[Valor],Tabela1[Mês],'Despesas - Mapa'!AH$2,Tabela1[Categoria],'Despesas - Mapa'!AG13) -> 0 | AJ13: Rolê | AK13: =SUMIFS(Tabela1[Valor],Tabela1[Mês],'Despesas - Mapa'!AK$2,Tabela1[Categoria],'Despesas - Mapa'!AJ13) -> 0
C14: Roupas | D14: =SUMIFS(Tabela1[Valor],Tabela1[Mês],'Despesas - Mapa'!D$2,Tabela1[Categoria],'Despesas - Mapa'!C14) -> 0 | F14: Roupas | G14: =SUMIFS(Tabela1[Valor],Tabela1[Mês],'Despesas - Mapa'!G$2,Tabela1[Categoria],'Despesas - Mapa'!F14) -> 0 | I14: Roupas | J14: =SUMIFS(Tabela1[Valor],Tabela1[Mês],'Despesas - Mapa'!J$2,Tabela1[Categoria],'Despesas - Mapa'!I14) -> 0 | L14: Roupas | M14: =SUMIFS(Tabela1[Valor],Tabela1[Mês],'Despesas - Mapa'!M$2,Tabela1[Categoria],'Despesas - Mapa'!L14) -> 0 | O14: Roupas | P14: =SUMIFS(Tabela1[Valor],Tabela1[Mês],'Despesas - Mapa'!P$2,Tabela1[Categoria],'Despesas - Mapa'!O14) -> 0 | R14: Roupas | S14: =SUMIFS(Tabela1[Valor],Tabela1[Mês],'Despesas - Mapa'!S$2,Tabela1[Categoria],'Despesas - Mapa'!R14) -> 0 | U14: Roupas | V14: =SUMIFS(Tabela1[Valor],Tabela1[Mês],'Despesas - Mapa'!V$2,Tabela1[Categoria],'Despesas - Mapa'!U14) -> 0 | X14: Roupas | Y14: =SUMIFS(Tabela1[Valor],Tabela1[Mês],'Despesas - Mapa'!Y$2,Tabela1[Categoria],'Despesas - Mapa'!X14) -> 0 | AA14: Roupas | AB14: =SUMIFS(Tabela1[Valor],Tabela1[Mês],'Despesas - Mapa'!AB$2,Tabela1[Categoria],'Despesas - Mapa'!AA14) -> 0 | AD14: Roupas | AE14: =SUMIFS(Tabela1[Valor],Tabela1[Mês],'Despesas - Mapa'!AE$2,Tabela1[Categoria],'Despesas - Mapa'!AD14) -> 0 | AG14: Roupas | AH14: =SUMIFS(Tabela1[Valor],Tabela1[Mês],'Despesas - Mapa'!AH$2,Tabela1[Categoria],'Despesas - Mapa'!AG14) -> 0 | AJ14: Roupas | AK14: =SUMIFS(Tabela1[Valor],Tabela1[Mês],'Despesas - Mapa'!AK$2,Tabela1[Categoria],'Despesas - Mapa'!AJ14) -> 0
C15: G. Gerais | D15: =SUMIFS(Tabela1[Valor],Tabela1[Mês],'Despesas - Mapa'!D$2,Tabela1[Categoria],'Despesas - Mapa'!C15) -> 0 | F15: G. Gerais | G15: =SUMIFS(Tabela1[Valor],Tabela1[Mês],'Despesas - Mapa'!G$2,Tabela1[Categoria],'Despesas - Mapa'!F15) -> 0 | I15: G. Gerais | J15: =SUMIFS(Tabela1[Valor],Tabela1[Mês],'Despesas - Mapa'!J$2,Tabela1[Categoria],'Despesas - Mapa'!I15) -> 0 | L15: G. Gerais | M15: =SUMIFS(Tabela1[Valor],Tabela1[Mês],'Despesas - Mapa'!M$2,Tabela1[Categoria],'Despesas - Mapa'!L15) -> 0 | O15: G. Gerais | P15: =SUMIFS(Tabela1[Valor],Tabela1[Mês],'Despesas - Mapa'!P$2,Tabela1[Categoria],'Despesas - Mapa'!O15) -> 0 | R15: G. Gerais | S15: =SUMIFS(Tabela1[Valor],Tabela1[Mês],'Despesas - Mapa'!S$2,Tabela1[Categoria],'Despesas - Mapa'!R15) -> 0 | U15: G. Gerais | V15: =SUMIFS(Tabela1[Valor],Tabela1[Mês],'Despesas - Mapa'!V$2,Tabela1[Categoria],'Despesas - Mapa'!U15) -> 0 | X15: G. Gerais | Y15: =SUMIFS(Tabela1[Valor],Tabela1[Mês],'Despesas - Mapa'!Y$2,Tabela1[Categoria],'Despesas - Mapa'!X15) -> 0 | AA15: G. Gerais | AB15: =SUMIFS(Tabela1[Valor],Tabela1[Mês],'Despesas - Mapa'!AB$2,Tabela1[Categoria],'Despesas - Mapa'!AA15) -> 0 | AD15: G. Gerais | AE15: =SUMIFS(Tabela1[Valor],Tabela1[Mês],'Despesas - Mapa'!AE$2,Tabela1[Categoria],'Despesas - Mapa'!AD15) -> 0 | AG15: G. Gerais | AH15: =SUMIFS(Tabela1[Valor],Tabela1[Mês],'Despesas - Mapa'!AH$2,Tabela1[Categoria],'Despesas - Mapa'!AG15) -> 0 | AJ15: G. Gerais | AK15: =SUMIFS(Tabela1[Valor],Tabela1[Mês],'Despesas - Mapa'!AK$2,Tabela1[Categoria],'Despesas - Mapa'!AJ15) -> 0
A17: Total | C17: =SUM(D7:D15) -> 0 | F17: =SUM(G7:G15) -> 0 | I17: =SUM(J7:J15) -> 0 | L17: =SUM(M7:M15) -> 0 | O17: =SUM(P7:P15) -> 0 | R17: =SUM(S7:S15) -> 0 | U17: =SUM(V7:V15) -> 0 | X17: =SUM(Y7:Y15) -> 0 | AA17: =SUM(AB7:AB15) -> 0 | AD17: =SUM(AE7:AE15) -> 0 | AG17: =SUM(AH7:AH15) -> 0 | AJ17: =SUM(AK7:AK15) -> 0

Sheet Gráfico - Anual
A2: Mês | C2: R. Líquida | D2: Investimentos | F2: Despesas | H2: Sld mês | I2: Sld. Atual | K2: Resultado - Total | N2: Despesas Fixas
A3: =PROPER(TEXT("01/01","MMMM")) -> Janeiro | C3: ='Receitas - Mapa'!B19 -> 0 | D3: =SUM('Receitas - Mapa'!B16:B17) -> 0 | F3: =SUM('Despesas - Mapa'!C17:C17) -> 0 | H3: =I3 -> 0 | I3: ='Despesas - Mapa'!D4 -> 0 | K3: Receita Bruta | L3: =SUM('Receitas - Mapa'!B4:M6) -> 150 | N3: ='Despesas - Mapa'!C7 -> Alimentação | O3: =SUM('Despesas - Mapa'!D7,'Despesas - Mapa'!G7,'Despesas - Mapa'!J7,'Despesas - Mapa'!M7,'Despesas - Mapa'!P7,'Despesas - Mapa'!S7,'Despesas - Mapa'!V7,'Despesas - Mapa'!Y7,'Despesas - Mapa'!AB7,'Despesas - Mapa'!AE7,'Despesas - Mapa'!AH7,'Despesas - Mapa'!AK7) -> 0
A4: =PROPER(TEXT("01/02","MMMM")) -> Fevereiro | C4: ='Receitas - Mapa'!C19 -> 0 | D4: =SUM('Receitas - Mapa'!C16:C17) -> 0 | F4: =SUM('Despesas - Mapa'!F17:G17) -> 0 | H4: =I4-I3 -> 0 | I4: ='Despesas - Mapa'!G4 -> 0 | K4: Perdas | L4: =SUM('Receitas - Mapa'!B9:M12) -> 0 | N4: ='Despesas - Mapa'!C8 -> G. Resid. | O4: =SUM('Despesas - Mapa'!D8,'Despesas - Mapa'!G8,'Despesas - Mapa'!J8,'Despesas - Mapa'!M8,'Despesas - Mapa'!P8,'Despesas - Mapa'!S8,'Despesas - Mapa'!V8,'Despesas - Mapa'!Y8,'Despesas - Mapa'!AB8,'Despesas - Mapa'!AE8,'Despesas - Mapa'!AH8,'Despesas - Mapa'!AK8) -> 0
A5: =PROPER(TEXT("01/03","MMMM")) -> Março | C5: ='Receitas - Mapa'!D19 -> 0 | D5: =SUM('Receitas - Mapa'!D16:D17) -> 0 | F5: =SUM('Despesas - Mapa'!I17:J17) -> 0 | H5: =I5-I4 -> 0 | I5: ='Despesas - Mapa'!J4 -> 0 | K5: Receita Líquida | L5: =SUM('Receitas - Mapa'!B4:M6)-SUM('Receitas - Mapa'!B15:M17)-SUM('Receitas - Mapa'!B9:M12) -> 100 | N5: ='Despesas - Mapa'!C9 -> Eletron e Jogos | O5: =SUM('Despesas - Mapa'!D9,'Despesas - Mapa'!G9,'Despesas - Mapa'!J9,'Despesas - Mapa'!M9,'Despesas - Mapa'!P9,'Despesas - Mapa'!S9,'Despesas - Mapa'!V9,'Despesas - Mapa'!Y9,'Despesas - Mapa'!AB9,'Despesas - Mapa'!AE9,'Despesas - Mapa'!AH9,'Despesas - Mapa'!AK9) -> 0
A6: =PROPER(TEXT("01/04","MMMM")) -> Abril | C6: ='Receitas - Mapa'!E19 -> 0 | D6: =SUM('Receitas - Mapa'!E16:E17) -> 0 | F6: =SUM('Despesas - Mapa'!L17:M17) -> 0 | H6: =I6-I5 -> 0 | I6: ='Despesas - Mapa'!M4 -> 0 | K6: Desp. Fixas | L6: =SUM('Despesas - Mapa'!D7:D14,'Despesas - Mapa'!G7:G14,'Despesas - Mapa'!J7:J14,'Despesas - Mapa'!M7:M14,'Despesas - Mapa'!P7:P14,'Despesas - Mapa'!S7:S14,'Despesas - Mapa'!V7:V14,'Despesas - Mapa'!Y7:Y14,'Despesas - Mapa'!AB7:AB14,'Despesas - Mapa'!AE7:AE14,'Despesas - Mapa'!AH7:AH14,'Despesas - Mapa'!AK7:AK14) -> 0 | N6: ='Despesas - Mapa'!C10 -> Cursos | O6: =SUM('Despesas - Mapa'!D10,'Despesas - Mapa'!G10,'Despesas - Mapa'!J10,'Despesas - Mapa'!M10,'Despesas - Mapa'!P10,'Despesas - Mapa'!S10,'Despesas - Mapa'!V10,'Despesas - Mapa'!Y10,'Despesas - Mapa'!AB10,'Despesas - Mapa'!AE10,'Despesas - Mapa'!AH10,'Despesas - Mapa'!AK10) -> 0
A7: =PROPER(TEXT("01/05","MMMM")) -> Maio | C7: ='Receitas - Mapa'!F19 -> 0 | D7: =SUM('Receitas - Mapa'!F16:F17) -> 0 | F7: =SUM('Despesas - Mapa'!O17:P17) -> 0 | H7: =I7-I6 -> 0 | I7: ='Despesas - Mapa'!P4 -> 0 | K7: Desp. Gerais | L7: =SUM('Despesas - Mapa'!D15:D15,'Despesas - Mapa'!G15:G15,'Despesas - Mapa'!J15:J15,'Despesas - Mapa'!M15:M15,'Despesas - Mapa'!P15:P15,'Despesas - Mapa'!S15:S15,'Despesas - Mapa'!V15:V15,'Despesas - Mapa'!Y15:Y15,'Despesas - Mapa'!AB15:AB15,'Despesas - Mapa'!AE15:AE15,'Despesas - Mapa'!AH15:AH15,'Despesas - Mapa'!AK15:AK15) -> 0 | N7: ='Despesas - Mapa'!C11 -> Farm. e Saúde. | O7: =SUM('Despesas - Mapa'!D11,'Despesas - Mapa'!G11,'Despesas - Mapa'!J11,'Despesas - Mapa'!M11,'Despesas - Mapa'!P11,'Despesas - Mapa'!S11,'Despesas - Mapa'!V11,'Despesas - Mapa'!Y11,'Despesas - Mapa'!AB11,'Despesas - Mapa'!AE11,'Despesas - Mapa'!AH11,'Despesas - Mapa'!AK11) -> 0
A8: =PROPER(TEXT("01/06","MMMM")) -> Junho | C8: ='Receitas - Mapa'!G19 -> 0 | D8: =SUM('Receitas - Mapa'!G16:G17) -> 0 | F8: =SUM('Despesas - Mapa'!R17:S17) -> 0 | H8: =I8-I7 -> 0 | I8: ='Despesas - Mapa'!S4 -> 0 | K8: Desp. Total | L8: =SUM(L6:L7) -> 0 | N8: ='Despesas - Mapa'!C12 -> Entret e Livros | O8: =SUM('Despesas - Mapa'!D12,'Despesas - Mapa'!G12,'Despesas - Mapa'!J12,'Despesas - Mapa'!M12,'Despesas - Mapa'!P12,'Despesas - Mapa'!S12,'Despesas - Mapa'!V12,'Despesas - Mapa'!Y12,'Despesas - Mapa'!AB12,'Despesas - Mapa'!AE12,'Despesas - Mapa'!AH12,'Despesas - Mapa'!AK12) -> 0
A9: =PROPER(TEXT("01/07","MMMM")) -> Julho | C9: ='Receitas - Mapa'!H19 -> 0 | D9: =SUM('Receitas - Mapa'!H16:H17) -> 0 | F9: =SUM('Despesas - Mapa'!U17:V17) -> 0 | H9: =I9-I8 -> 0 | I9: ='Despesas - Mapa'!V4 -> 0 | K9: Saldo Anual | L9: ='Despesas - Mapa'!AK4 -> 100 | N9: ='Despesas - Mapa'!C13 -> Rolê | O9: =SUM('Despesas - Mapa'!D13,'Despesas - Mapa'!G13,'Despesas - Mapa'!J13,'Despesas - Mapa'!M13,'Despesas - Mapa'!P13,'Despesas - Mapa'!S13,'Despesas - Mapa'!V13,'Despesas - Mapa'!Y13,'Despesas - Mapa'!AB13,'Despesas - Mapa'!AE13,'Despesas - Mapa'!AH13,'Despesas - Mapa'!AK13) -> 0
A10: =PROPER(TEXT("01/08","MMMM")) -> Agosto | C10: ='Receitas - Mapa'!I19 -> 0 | D10: =SUM('Receitas - Mapa'!I16:I17) -> 0 | F10: =SUM('Despesas - Mapa'!X17:Y17) -> 0 | H10: =I10-I9 -> 0 | I10: ='Despesas - Mapa'!Y4 -> 0 | K10: Investimento | L10: ='Gráfico - Anual'!D15 -> 50 | N10: ='Despesas - Mapa'!C14 -> Roupas | O10: =SUM('Despesas - Mapa'!D14,'Despesas - Mapa'!G14,'Despesas - Mapa'!J14,'Despesas - Mapa'!M14,'Despesas - Mapa'!P14,'Despesas - Mapa'!S14,'Despesas - Mapa'!V14,'Despesas - Mapa'!Y14,'Despesas - Mapa'!AB14,'Despesas - Mapa'!AE14,'Despesas - Mapa'!AH14,'Despesas - Mapa'!AK14) -> 0
A11: =PROPER(TEXT("01/09","MMMM")) -> Setembro | C11: ='Receitas - Mapa'!J19 -> 0 | D11: =SUM('Receitas - Mapa'!J16:J17) -> 0 | F11: =SUM('Despesas - Mapa'!AA17:AB17) -> 0 | H11: =I11-I10 -> 0 | I11: ='Despesas - Mapa'!AB4 -> 0 | N11: Total | O11: =SUM(O3:O10) -> 0
A12: =PROPER(TEXT("01/10","MMMM")) -> Outubro | C12: ='Receitas - Mapa'!K19 -> 100 | D12: =SUM('Receitas - Mapa'!K16:K17) -> 50 | F12: =SUM('Despesas - Mapa'!AD17:AE17) -> 0 | H12: =I12-I11 -> 100 | I12: ='Despesas - Mapa'!AE4 -> 100
A13: =PROPER(TEXT("01/11","MMMM")) -> Novembro | C13: ='Receitas - Mapa'!L19 -> 0 | D13: =SUM('Receitas - Mapa'!L16:L17) -> 0 | F13: =SUM('Despesas - Mapa'!AG17:AH17) -> 0 | H13: =I13-I12 -> 0 | I13: ='Despesas - Mapa'!AH4 -> 100
A14: =PROPER(TEXT("01/12","MMMM")) -> Dezembro | C14: ='Receitas - Mapa'!M19 -> 0 | D14: =SUM('Receitas - Mapa'!M16:M17) -> 0 | F14: =SUM('Despesas - Mapa'!AJ17:AK17) -> 0 | H14: =I14-I13 -> 0 | I14: ='Despesas - Mapa'!AK4 -> 100
A15: Total | C15: =SUM(C3:C14) -> 100 | D15: =SUM(D3:D14) -> 50 | F15: =SUM(F3:F14) -> 0 | H15: Saldo Anual | I15: ='Gráfico - Anual'!L9 -> 100
A16: Média | C16: =AVERAGE(C3:C14) -> 8.3333333 | D16: =AVERAGE(D3:D14) -> 4.1666667 | F16: =AVERAGE(F3:F14) -> 0
A17: 1º Sem. | C17: =SUM(C3:C8) -> 0 | D17: =SUM(D3:D8) -> 0 | F17: =SUM(F3:F8) -> 0
A18: 2º Sem. | C18: =SUM($C$9:$C$14) -> 100 | D18: =SUM($D$9:$D$14) -> 50 | F18: =SUM($F$9:$F$14) -> 0
