Workbook
Name Contas: 'Validação de Dados'!$B$5:$B$10
Name Dash: 'Gráfico Anual'!$A$1:$P$26
Name Despesas: 'Validação de Dados'!$E$5:$E$16
Name Investimentos: 'Validação de Dados'!$G$19:$G$20
Name Meses: 'Validação de Dados'!$M$5:$M$16
Name Pagamento: 'Validação de Dados'!$B$9:$B$10
Name Perdas: 'Validação de Dados'!$G$5:$G$9
Name Receita_Líquida: 'Validação de Dados'!$I$5:$I$16
Name Receitas: 'Validação de Dados'!$G$12:$G$16
Name Transferir: 'Validação de Dados'!$B$5:$B$8

Sheet Validação de Dados
B2: *Faça alterações nos valores em azul como preferir, porém para adicionar ou remover valores será necessário alterar a planilha onde for preciso.
B4: Contas | C4: Saldo Inicial | E4: Despesas | G4: Perdas | I4: Receita Líquida | K4: Transferir | M4: Meses
B5: Banco 1 | C5: 0 | E5: Alimentação | G5: Inss | I5: {=Receitas} -> Salário | K5: {=Transferir} -> Banco 1 | M5: Janeiro
B6: Banco 2 | C6: 0 | E6: Transp./ Carro | G6: T. Transporte | I6: Vendas | K6: Banco 2 | M6: Fevereiro
B7: Dinheiro | C7: 0 | E7: Condomínio | G7: Taxa | I7: Aluguel | K7: Dinheiro | M7: Março
B8: Savings | C8: 0 | E8: Curso | G8: Imposto | I8: Rendimentos | K8: Savings | M8: Abril
B9: Dívidas | C9: 0 | E9: Eletrônicos | G9: Perdas Outros | I9: Receitas Outros | M9: Maio
B10: C. Crédito | C10: 0 | E10: Farm. e Saúde. | I10: {=Perdas} -> Inss | K10: Pagamento | M10: Junho
E11: G. Residencial | G11: Receitas | I11: T. Transporte | K11: {=Pagamento} -> Dívidas | M11: Julho
E12: Gasolina | G12: Salário | I12: Taxa | K12: C. Crédito | M12: Agosto
E13: Jogos/ Livros | G13: Vendas | I13: Imposto | M13: Setembro
E14: Rolê/ Entret. | G14: Aluguel | I14: Perdas Outros | M14: Outubro
E15: Roupas | G15: Rendimentos | I15: {=Investimentos} -> CDI | M15: Novembro
E16: G. Gerais | G16: Receitas Outros | I16: Tesouro Direto | M16: Dezembro
G18: Investimentos
G19: CDI
G20: Tesouro Direto

Sheet Saldo & Mov.
F1: Valor
B2: =IF($C$5="",PROPER(TEXT(TODAY(),"MMMM")),PROPER(TEXT($C$5,"MMMM"))) -> Abril | C2: Total | E2: {=IF(B3="Despesas",Despesas,IF(B3="Receita Líquida",Receita_Líquida,""))} -> Alimentação | F2: {=IF(B3="Despesas",_xlfn._xlws.FILTER('Despesas Gerais'!B7:M18,'Despesas Gerais'!B2:M2=B2),IF(B3="Receita Líquida",_xlfn._xlws.FILTER('Receita Líquida'!B5:M16,'Receita Líquida'!B4:M4=B2),""))} -> 0
B3: Despesas | C3: =IF(B3="Despesas",HLOOKUP(B2,'Despesas Gerais'!B2:M20,19,FALSE),IF(B3="Receita Líquida",HLOOKUP(B2,'Receita Líquida'!B4:M18,15,FALSE),"")) -> 0 | E3: Transp./ Carro | F3: 0
E4: Condomínio | F4: 0
B5: Contas - Hoje | C5: =TODAY() -> 46128 | E5: Curso | F5: 0 | K5: Contas | L5: =EOMONTH(TODAY(),0)+1 -> 46143
B6: Saldo | C6: =SUM(C7:C9)-SUM(C11:C12) -> 0 | E6: Eletrônicos | F6: 0 | K6: Saldo | L6: =SUM(L7:L9)-SUM(L11:L12) -> 0
B7: {=Contas} -> Banco 1 | C7: {=ROUND(SUM(SUMIFS(Tabela1[Valor],Tabela1[Operação],{"Receitas";"Transferir"},Tabela1[Conta],B7,Tabela1[Data],"<="&(IF(ISBLANK($C$5),TODAY(),$C$5))))-SUMIFS(Tabela1[Valor],Tabela1[Operação],"<>Receitas",Tabela1[Operação],"<>Transferir",Tabela1[Conta],B7,Tabela1[Data],"<="&(IF(ISBLANK($C$5),TODAY(),$C$5))) -SUMIFS(Tabela1[Valor],Tabela1[Categoria],B7,Tabela1[Data],"<="&(IF(ISBLANK($C$5),TODAY(),$C$5)))+VLOOKUP(B7,'Validação de Dados'!$B$5:$C$10,2,FALSE),2)} -> 0 | E7: Farm. e Saúde. | F7: 0 | K7: {=Contas} -> Banco 1 | L7: {=ROUND(SUM(SUMIFS(Tabela1[Valor],Tabela1[Operação],{"Receitas";"Transferir"},Tabela1[Conta],K7,Tabela1[Data],"<="&(IF(ISBLANK($L$5),TODAY(),$L$5))))-SUMIFS(Tabela1[Valor],Tabela1[Operação],"<>Receitas",Tabela1[Operação],"<>Transferir",Tabela1[Conta],K7,Tabela1[Data],"<="&(IF(ISBLANK($L$5),TODAY(),$L$5))) -SUMIFS(Tabela1[Valor],Tabela1[Categoria],K7,Tabela1[Data],"<="&(IF(ISBLANK($L$5),TODAY(),$L$5)))+VLOOKUP(K7,'Validação de Dados'!$B$5:$C$10,2,FALSE),2)} -> 0
B8: Banco 2 | C8: {=ROUND(SUM(SUMIFS(Tabela1[Valor],Tabela1[Operação],{"Receitas";"Transferir"},Tabela1[Conta],B8,Tabela1[Data],"<="&(IF(ISBLANK($C$5),TODAY(),$C$5))))-SUMIFS(Tabela1[Valor],Tabela1[Operação],"<>Receitas",Tabela1[Operação],"<>Transferir",Tabela1[Conta],B8,Tabela1[Data],"<="&(IF(ISBLANK($C$5),TODAY(),$C$5))) -SUMIFS(Tabela1[Valor],Tabela1[Categoria],B8,Tabela1[Data],"<="&(IF(ISBLANK($C$5),TODAY(),$C$5)))+VLOOKUP(B8,'Validação de Dados'!$B$5:$C$10,2,FALSE),2)} -> 0 | E8: G. Residencial | F8: 0 | K8: Banco 2 | L8: {=ROUND(SUM(SUMIFS(Tabela1[Valor],Tabela1[Operação],{"Receitas";"Transferir"},Tabela1[Conta],K8,Tabela1[Data],"<="&(IF(ISBLANK($L$5),TODAY(),$L$5))))-SUMIFS(Tabela1[Valor],Tabela1[Operação],"<>Receitas",Tabela1[Operação],"<>Transferir",Tabela1[Conta],K8,Tabela1[Data],"<="&(IF(ISBLANK($L$5),TODAY(),$L$5))) -SUMIFS(Tabela1[Valor],Tabela1[Categoria],K8,Tabela1[Data],"<="&(IF(ISBLANK($L$5),TODAY(),$L$5)))+VLOOKUP(K8,'Validação de Dados'!$B$5:$C$10,2,FALSE),2)} -> 0
B9: Dinheiro | C9: {=ROUND(SUM(SUMIFS(Tabela1[Valor],Tabela1[Operação],{"Receitas";"Transferir"},Tabela1[Conta],B9,Tabela1[Data],"<="&(IF(ISBLANK($C$5),TODAY(),$C$5))))-SUMIFS(Tabela1[Valor],Tabela1[Operação],"<>Receitas",Tabela1[Operação],"<>Transferir",Tabela1[Conta],B9,Tabela1[Data],"<="&(IF(ISBLANK($C$5),TODAY(),$C$5)))-SUMIFS(Tabela1[Valor],Tabela1[Categoria],B9,Tabela1[Data],"<="&(IF(ISBLANK($C$5),TODAY(),$C$5)))+VLOOKUP(B9,'Validação de Dados'!$B$5:$C$10,2,FALSE),2)} -> 0 | E9: Gasolina | F9: 0 | K9: Dinheiro | L9: {=ROUND(SUM(SUMIFS(Tabela1[Valor],Tabela1[Operação],{"Receitas";"Transferir"},Tabela1[Conta],K9,Tabela1[Data],"<="&(IF(ISBLANK($L$5),TODAY(),$L$5))))-SUMIFS(Tabela1[Valor],Tabela1[Operação],"<>Receitas",Tabela1[Operação],"<>Transferir",Tabela1[Conta],K9,Tabela1[Data],"<="&(IF(ISBLANK($L$5),TODAY(),$L$5))) -SUMIFS(Tabela1[Valor],Tabela1[Categoria],K9,Tabela1[Data],"<="&(IF(ISBLANK($L$5),TODAY(),$L$5)))+VLOOKUP(K9,'Validação de Dados'!$B$5:$C$10,2,FALSE),2)} -> 0
B10: Savings | C10: {=ROUND(SUM(SUMIFS(Tabela1[Valor],Tabela1[Operação],{"Receitas";"Transferir"},Tabela1[Conta],B10,Tabela1[Data],"<="&(IF(ISBLANK($C$5),TODAY(),$C$5))))-SUMIFS(Tabela1[Valor],Tabela1[Operação],"<>Receitas",Tabela1[Operação],"<>Transferir",Tabela1[Conta],B10,Tabela1[Data],"<="&(IF(ISBLANK($C$5),TODAY(),$C$5)))-SUMIFS(Tabela1[Valor],Tabela1[Categoria],B10,Tabela1[Data],"<="&(IF(ISBLANK($C$5),TODAY(),$C$5)))+VLOOKUP(B10,'Validação de Dados'!$B$5:$C$10,2,FALSE),2)} -> 0 | E10: Jogos/ Livros | F10: 0 | K10: Savings | L10: {=ROUND(SUM(SUMIFS(Tabela1[Valor],Tabela1[Operação],{"Receitas";"Transferir"},Tabela1[Conta],K10,Tabela1[Data],"<="&(IF(ISBLANK($L$5),TODAY(),$L$5))))-SUMIFS(Tabela1[Valor],Tabela1[Operação],"<>Receitas",Tabela1[Operação],"<>Transferir",Tabela1[Conta],K10,Tabela1[Data],"<="&(IF(ISBLANK($L$5),TODAY(),$L$5))) -SUMIFS(Tabela1[Valor],Tabela1[Categoria],K10,Tabela1[Data],"<="&(IF(ISBLANK($L$5),TODAY(),$L$5)))+VLOOKUP(K10,'Validação de Dados'!$B$5:$C$10,2,FALSE),2)} -> 0
B11: Dívidas | C11: =ROUND(SUMIFS(Tabela1[Valor],Tabela1[Operação],"Despesas",Tabela1[Conta],B11,Tabela1[Data],"<="&(IF(ISBLANK($C$5),TODAY(),$C$5)))-SUMIFS(Tabela1[Valor],Tabela1[Operação],"Pagamento",Tabela1[Categoria],B11,Tabela1[Data],"<="&(IF(ISBLANK($C$5),TODAY(),$C$5)))+VLOOKUP(B11,'Validação de Dados'!$B$5:$C$10,2,FALSE),2) -> 0 | E11: Rolê/ Entret. | F11: 0 | K11: Dívidas | L11: =ROUND(SUMIFS(Tabela1[Valor],Tabela1[Operação],"Despesas",Tabela1[Conta],K11,Tabela1[Data],"<="&(IF(ISBLANK($L$5),TODAY(),$L$5)))-SUMIFS(Tabela1[Valor],Tabela1[Operação],"Pagamento",Tabela1[Categoria],K11,Tabela1[Data],"<="&(IF(ISBLANK($L$5),TODAY(),$L$5)))+VLOOKUP(K11,'Validação de Dados'!$B$5:$C$10,2,FALSE),2) -> 0
B12: C. Crédito | C12: =ROUND(SUMIFS(Tabela1[Valor],Tabela1[Operação],"Despesas",Tabela1[Conta],B12,Tabela1[Data],"<="&(IF(ISBLANK($C$5),TODAY(),$C$5)))-SUMIFS(Tabela1[Valor],Tabela1[Operação],"Pagamento",Tabela1[Categoria],B12,Tabela1[Data],"<="&(IF(ISBLANK($C$5),TODAY(),$C$5)))+VLOOKUP(B12,'Validação de Dados'!$B$5:$C$10,2,FALSE),2) -> 0 | E12: Roupas | F12: 0 | K12: C. Crédito | L12: =ROUND(SUMIFS(Tabela1[Valor],Tabela1[Operação],"Despesas",Tabela1[Conta],K12,Tabela1[Data],"<="&(IF(ISBLANK($L$5),TODAY(),$L$5)))-SUMIFS(Tabela1[Valor],Tabela1[Operação],"Pagamento",Tabela1[Categoria],K12,Tabela1[Data],"<="&(IF(ISBLANK($L$5),TODAY(),$L$5)))+VLOOKUP(K12,'Validação de Dados'!$B$5:$C$10,2,FALSE),2) -> 0
E13: G. Gerais | F13: 0
B14: =PROPER(TEXT(EOMONTH(TODAY(),1),"MMMM")) -> Maio | C14: =L6 -> 0
A16: =SUBTOTAL(2,Tabela1[Data]) -> 0 | B16: Data | C16: Mês | D16: Operação | E16: Categoria | F16: Conta | G16: Valor | H16: Descrição
C17: =IF(ISBLANK(B17),"",PROPER(TEXT(B17,"MMMM")))
C18: =IF(ISBLANK(B18),"",PROPER(TEXT(B18,"MMMM")))
C19: =IF(ISBLANK(B19),"",PROPER(TEXT(B19,"MMMM"))) | H19: Tab para criar nova linha.
C235: =IF(ISBLANK(B235),"",PROPER(TEXT(B235,"MMMM")))
C236: =IF(ISBLANK(B236),"",PROPER(TEXT(B236,"MMMM")))
C245: =IF(ISBLANK(B245),"",PROPER(TEXT(B245,"MMMM"))) | D245: =IF(ISBLANK(C245),"",PROPER(TEXT(C245,"MMMM"))) | E245: =IF(ISBLANK(D245),"",PROPER(TEXT(D245,"MMMM"))) | F245: =IF(ISBLANK(E245),"",PROPER(TEXT(E245,"MMMM"))) | G245: =IF(ISBLANK(F245),"",PROPER(TEXT(F245,"MMMM")))
C254: =IF(ISBLANK(B254),"",PROPER(TEXT(B254,"MMMM")))
C255: =IF(ISBLANK(B255),"",PROPER(TEXT(B255,"MMMM")))
C256: =IF(ISBLANK(B256),"",PROPER(TEXT(B256,"MMMM")))
C257: =IF(ISBLANK(B257),"",PROPER(TEXT(B257,"MMMM")))
C258: =IF(ISBLANK(B258),"",PROPER(TEXT(B258,"MMMM")))
C259: =IF(ISBLANK(B259),"",PROPER(TEXT(B259,"MMMM")))
C260: =IF(ISBLANK(B260),"",PROPER(TEXT(B260,"MMMM")))
C261: =IF(ISBLANK(B261),"",PROPER(TEXT(B261,"MMMM")))
C262: =IF(ISBLANK(B262),"",PROPER(TEXT(B262,"MMMM")))
C263: =IF(ISBLANK(B263),"",PROPER(TEXT(B263,"MMMM")))
C264: =IF(ISBLANK(B264),"",PROPER(TEXT(B264,"MMMM")))
C265: =IF(ISBLANK(B265),"",PROPER(TEXT(B265,"MMMM")))
... C772: =IF(ISBLANK(B772),"",PROPER(TEXT(B772,"MMMM")))

Sheet Receita Líquida
A2: Saldo Inicial | B2: =SUM('Validação de Dados'!C5:C8)-SUM('Validação de Dados'!C9:C10) -> 0
B4: {=TRANSPOSE(Meses)} -> Janeiro | C4: Fevereiro | D4: Março | E4: Abril | F4: Maio | G4: Junho | H4: Julho | I4: Agosto | J4: Setembro | K4: Outubro | L4: Novembro | M4: Dezembro
A5: {=Receita_Líquida} -> Salário | B5: =SUMIFS(Tabela1[Valor],Tabela1[Mês],B$4,Tabela1[Categoria],$A5) -> 0 | C5: =SUMIFS(Tabela1[Valor],Tabela1[Mês],C$4,Tabela1[Categoria],$A5) -> 0 | D5: =SUMIFS(Tabela1[Valor],Tabela1[Mês],D$4,Tabela1[Categoria],$A5) -> 0 | E5: =SUMIFS(Tabela1[Valor],Tabela1[Mês],E$4,Tabela1[Categoria],$A5) -> 0 | F5: =SUMIFS(Tabela1[Valor],Tabela1[Mês],F$4,Tabela1[Categoria],$A5) -> 0 | G5: =SUMIFS(Tabela1[Valor],Tabela1[Mês],G$4,Tabela1[Categoria],$A5) -> 0 | H5: =SUMIFS(Tabela1[Valor],Tabela1[Mês],H$4,Tabela1[Categoria],$A5) -> 0 | I5: =SUMIFS(Tabela1[Valor],Tabela1[Mês],I$4,Tabela1[Categoria],$A5) -> 0 | ... M5: =SUMIFS(Tabela1[Valor],Tabela1[Mês],M$4,Tabela1[Categoria],$A5) -> 0
A6: Vendas | B6: =SUMIFS(Tabela1[Valor],Tabela1[Mês],B$4,Tabela1[Categoria],$A6) -> 0 | C6: =SUMIFS(Tabela1[Valor],Tabela1[Mês],C$4,Tabela1[Categoria],$A6) -> 0 | D6: =SUMIFS(Tabela1[Valor],Tabela1[Mês],D$4,Tabela1[Categoria],$A6) -> 0 | E6: =SUMIFS(Tabela1[Valor],Tabela1[Mês],E$4,Tabela1[Categoria],$A6) -> 0 | F6: =SUMIFS(Tabela1[Valor],Tabela1[Mês],F$4,Tabela1[Categoria],$A6) -> 0 | G6: =SUMIFS(Tabela1[Valor],Tabela1[Mês],G$4,Tabela1[Categoria],$A6) -> 0 | H6: =SUMIFS(Tabela1[Valor],Tabela1[Mês],H$4,Tabela1[Categoria],$A6) -> 0 | I6: =SUMIFS(Tabela1[Valor],Tabela1[Mês],I$4,Tabela1[Categoria],$A6) -> 0 | ... M6: =SUMIFS(Tabela1[Valor],Tabela1[Mês],M$4,Tabela1[Categoria],$A6) -> 0
A7: Aluguel | B7: =SUMIFS(Tabela1[Valor],Tabela1[Mês],B$4,Tabela1[Categoria],$A7) -> 0 | C7: =SUMIFS(Tabela1[Valor],Tabela1[Mês],C$4,Tabela1[Categoria],$A7) -> 0 | D7: =SUMIFS(Tabela1[Valor],Tabela1[Mês],D$4,Tabela1[Categoria],$A7) -> 0 | E7: =SUMIFS(Tabela1[Valor],Tabela1[Mês],E$4,Tabela1[Categoria],$A7) -> 0 | F7: =SUMIFS(Tabela1[Valor],Tabela1[Mês],F$4,Tabela1[Categoria],$A7) -> 0 | G7: =SUMIFS(Tabela1[Valor],Tabela1[Mês],G$4,Tabela1[Categoria],$A7) -> 0 | H7: =SUMIFS(Tabela1[Valor],Tabela1[Mês],H$4,Tabela1[Categoria],$A7) -> 0 | I7: =SUMIFS(Tabela1[Valor],Tabela1[Mês],I$4,Tabela1[Categoria],$A7) -> 0 | ... M7: =SUMIFS(Tabela1[Valor],Tabela1[Mês],M$4,Tabela1[Categoria],$A7) -> 0
A8: Rendimentos | B8: =SUMIFS(Tabela1[Valor],Tabela1[Mês],B$4,Tabela1[Categoria],$A8) -> 0 | C8: =SUMIFS(Tabela1[Valor],Tabela1[Mês],C$4,Tabela1[Categoria],$A8) -> 0 | D8: =SUMIFS(Tabela1[Valor],Tabela1[Mês],D$4,Tabela1[Categoria],$A8) -> 0 | E8: =SUMIFS(Tabela1[Valor],Tabela1[Mês],E$4,Tabela1[Categoria],$A8) -> 0 | F8: =SUMIFS(Tabela1[Valor],Tabela1[Mês],F$4,Tabela1[Categoria],$A8) -> 0 | G8: =SUMIFS(Tabela1[Valor],Tabela1[Mês],G$4,Tabela1[Categoria],$A8) -> 0 | H8: =SUMIFS(Tabela1[Valor],Tabela1[Mês],H$4,Tabela1[Categoria],$A8) -> 0 | I8: =SUMIFS(Tabela1[Valor],Tabela1[Mês],I$4,Tabela1[Categoria],$A8) -> 0 | ... M8: =SUMIFS(Tabela1[Valor],Tabela1[Mês],M$4,Tabela1[Categoria],$A8) -> 0
A9: Receitas Outros | B9: =SUMIFS(Tabela1[Valor],Tabela1[Mês],B$4,Tabela1[Categoria],$A9) -> 0 | C9: =SUMIFS(Tabela1[Valor],Tabela1[Mês],C$4,Tabela1[Categoria],$A9) -> 0 | D9: =SUMIFS(Tabela1[Valor],Tabela1[Mês],D$4,Tabela1[Categoria],$A9) -> 0 | E9: =SUMIFS(Tabela1[Valor],Tabela1[Mês],E$4,Tabela1[Categoria],$A9) -> 0 | F9: =SUMIFS(Tabela1[Valor],Tabela1[Mês],F$4,Tabela1[Categoria],$A9) -> 0 | G9: =SUMIFS(Tabela1[Valor],Tabela1[Mês],G$4,Tabela1[Categoria],$A9) -> 0 | H9: =SUMIFS(Tabela1[Valor],Tabela1[Mês],H$4,Tabela1[Categoria],$A9) -> 0 | I9: =SUMIFS(Tabela1[Valor],Tabela1[Mês],I$4,Tabela1[Categoria],$A9) -> 0 | ... M9: =SUMIFS(Tabela1[Valor],Tabela1[Mês],M$4,Tabela1[Categoria],$A9) -> 0
A10: Inss | B10: =SUMIFS(Tabela1[Valor],Tabela1[Mês],B$4,Tabela1[Categoria],$A10) -> 0 | C10: =SUMIFS(Tabela1[Valor],Tabela1[Mês],C$4,Tabela1[Categoria],$A10) -> 0 | D10: =SUMIFS(Tabela1[Valor],Tabela1[Mês],D$4,Tabela1[Categoria],$A10) -> 0 | E10: =SUMIFS(Tabela1[Valor],Tabela1[Mês],E$4,Tabela1[Categoria],$A10) -> 0 | F10: =SUMIFS(Tabela1[Valor],Tabela1[Mês],F$4,Tabela1[Categoria],$A10) -> 0 | G10: =SUMIFS(Tabela1[Valor],Tabela1[Mês],G$4,Tabela1[Categoria],$A10) -> 0 | H10: =SUMIFS(Tabela1[Valor],Tabela1[Mês],H$4,Tabela1[Categoria],$A10) -> 0 | I10: =SUMIFS(Tabela1[Valor],Tabela1[Mês],I$4,Tabela1[Categoria],$A10) -> 0 | ... M10: =SUMIFS(Tabela1[Valor],Tabela1[Mês],M$4,Tabela1[Categoria],$A10) -> 0
A11: T. Transporte | B11: =SUMIFS(Tabela1[Valor],Tabela1[Mês],B$4,Tabela1[Categoria],$A11) -> 0 | C11: =SUMIFS(Tabela1[Valor],Tabela1[Mês],C$4,Tabela1[Categoria],$A11) -> 0 | D11: =SUMIFS(Tabela1[Valor],Tabela1[Mês],D$4,Tabela1[Categoria],$A11) -> 0 | E11: =SUMIFS(Tabela1[Valor],Tabela1[Mês],E$4,Tabela1[Categoria],$A11) -> 0 | F11: =SUMIFS(Tabela1[Valor],Tabela1[Mês],F$4,Tabela1[Categoria],$A11) -> 0 | G11: =SUMIFS(Tabela1[Valor],Tabela1[Mês],G$4,Tabela1[Categoria],$A11) -> 0 | H11: =SUMIFS(Tabela1[Valor],Tabela1[Mês],H$4,Tabela1[Categoria],$A11) -> 0 | I11: =SUMIFS(Tabela1[Valor],Tabela1[Mês],I$4,Tabela1[Categoria],$A11) -> 0 | ... M11: =SUMIFS(Tabela1[Valor],Tabela1[Mês],M$4,Tabela1[Categoria],$A11) -> 0
A12: Taxa | B12: =SUMIFS(Tabela1[Valor],Tabela1[Mês],B$4,Tabela1[Categoria],$A12) -> 0 | C12: =SUMIFS(Tabela1[Valor],Tabela1[Mês],C$4,Tabela1[Categoria],$A12) -> 0 | D12: =SUMIFS(Tabela1[Valor],Tabela1[Mês],D$4,Tabela1[Categoria],$A12) -> 0 | E12: =SUMIFS(Tabela1[Valor],Tabela1[Mês],E$4,Tabela1[Categoria],$A12) -> 0 | F12: =SUMIFS(Tabela1[Valor],Tabela1[Mês],F$4,Tabela1[Categoria],$A12) -> 0 | G12: =SUMIFS(Tabela1[Valor],Tabela1[Mês],G$4,Tabela1[Categoria],$A12) -> 0 | H12: =SUMIFS(Tabela1[Valor],Tabela1[Mês],H$4,Tabela1[Categoria],$A12) -> 0 | I12: =SUMIFS(Tabela1[Valor],Tabela1[Mês],I$4,Tabela1[Categoria],$A12) -> 0 | ... M12: =SUMIFS(Tabela1[Valor],Tabela1[Mês],M$4,Tabela1[Categoria],$A12) -> 0
A13: Imposto | B13: =SUMIFS(Tabela1[Valor],Tabela1[Mês],B$4,Tabela1[Categoria],$A13) -> 0 | C13: =SUMIFS(Tabela1[Valor],Tabela1[Mês],C$4,Tabela1[Categoria],$A13) -> 0 | D13: =SUMIFS(Tabela1[Valor],Tabela1[Mês],D$4,Tabela1[Categoria],$A13) -> 0 | E13: =SUMIFS(Tabela1[Valor],Tabela1[Mês],E$4,Tabela1[Categoria],$A13) -> 0 | F13: =SUMIFS(Tabela1[Valor],Tabela1[Mês],F$4,Tabela1[Categoria],$A13) -> 0 | G13: =SUMIFS(Tabela1[Valor],Tabela1[Mês],G$4,Tabela1[Categoria],$A13) -> 0 | H13: =SUMIFS(Tabela1[Valor],Tabela1[Mês],H$4,Tabela1[Categoria],$A13) -> 0 | I13: =SUMIFS(Tabela1[Valor],Tabela1[Mês],I$4,Tabela1[Categoria],$A13) -> 0 | ... M13: =SUMIFS(Tabela1[Valor],Tabela1[Mês],M$4,Tabela1[Categoria],$A13) -> 0
A14: Perdas Outros | B14: =SUMIFS(Tabela1[Valor],Tabela1[Mês],B$4,Tabela1[Categoria],$A14) -> 0 | C14: =SUMIFS(Tabela1[Valor],Tabela1[Mês],C$4,Tabela1[Categoria],$A14) -> 0 | D14: =SUMIFS(Tabela1[Valor],Tabela1[Mês],D$4,Tabela1[Categoria],$A14) -> 0 | E14: =SUMIFS(Tabela1[Valor],Tabela1[Mês],E$4,Tabela1[Categoria],$A14) -> 0 | F14: =SUMIFS(Tabela1[Valor],Tabela1[Mês],F$4,Tabela1[Categoria],$A14) -> 0 | G14: =SUMIFS(Tabela1[Valor],Tabela1[Mês],G$4,Tabela1[Categoria],$A14) -> 0 | H14: =SUMIFS(Tabela1[Valor],Tabela1[Mês],H$4,Tabela1[Categoria],$A14) -> 0 | I14: =SUMIFS(Tabela1[Valor],Tabela1[Mês],I$4,Tabela1[Categoria],$A14) -> 0 | ... M14: =SUMIFS(Tabela1[Valor],Tabela1[Mês],M$4,Tabela1[Categoria],$A14) -> 0
A15: CDI | B15: =SUMIFS(Tabela1[Valor],Tabela1[Mês],B$4,Tabela1[Categoria],$A15) -> 0 | C15: =SUMIFS(Tabela1[Valor],Tabela1[Mês],C$4,Tabela1[Categoria],$A15) -> 0 | D15: =SUMIFS(Tabela1[Valor],Tabela1[Mês],D$4,Tabela1[Categoria],$A15) -> 0 | E15: =SUMIFS(Tabela1[Valor],Tabela1[Mês],E$4,Tabela1[Categoria],$A15) -> 0 | F15: =SUMIFS(Tabela1[Valor],Tabela1[Mês],F$4,Tabela1[Categoria],$A15) -> 0 | G15: =SUMIFS(Tabela1[Valor],Tabela1[Mês],G$4,Tabela1[Categoria],$A15) -> 0 | H15: =SUMIFS(Tabela1[Valor],Tabela1[Mês],H$4,Tabela1[Categoria],$A15) -> 0 | I15: =SUMIFS(Tabela1[Valor],Tabela1[Mês],I$4,Tabela1[Categoria],$A15) -> 0 | ... M15: =SUMIFS(Tabela1[Valor],Tabela1[Mês],M$4,Tabela1[Categoria],$A15) -> 0
A16: Tesouro Direto | B16: =SUMIFS(Tabela1[Valor],Tabela1[Mês],B$4,Tabela1[Categoria],$A16) -> 0 | C16: =SUMIFS(Tabela1[Valor],Tabela1[Mês],C$4,Tabela1[Categoria],$A16) -> 0 | D16: =SUMIFS(Tabela1[Valor],Tabela1[Mês],D$4,Tabela1[Categoria],$A16) -> 0 | E16: =SUMIFS(Tabela1[Valor],Tabela1[Mês],E$4,Tabela1[Categoria],$A16) -> 0 | F16: =SUMIFS(Tabela1[Valor],Tabela1[Mês],F$4,Tabela1[Categoria],$A16) -> 0 | G16: =SUMIFS(Tabela1[Valor],Tabela1[Mês],G$4,Tabela1[Categoria],$A16) -> 0 | H16: =SUMIFS(Tabela1[Valor],Tabela1[Mês],H$4,Tabela1[Categoria],$A16) -> 0 | I16: =SUMIFS(Tabela1[Valor],Tabela1[Mês],I$4,Tabela1[Categoria],$A16) -> 0 | ... M16: =SUMIFS(Tabela1[Valor],Tabela1[Mês],M$4,Tabela1[Categoria],$A16) -> 0
A18: Total Geral | B18: =ROUND(SUM(B5:B9)-SUM(B10:B16),2)+B20+B2 -> 0 | C18: =ROUND(SUM(C5:C9)-SUM(C10:C16),2) -> 0 | D18: =ROUND(SUM(D5:D9)-SUM(D10:D16),2) -> 0 | E18: =ROUND(SUM(E5:E9)-SUM(E10:E16),2) -> 0 | F18: =ROUND(SUM(F5:F9)-SUM(F10:F16),2) -> 0 | G18: =ROUND(SUM(G5:G9)-SUM(G10:G16),2) -> 0 | H18: =ROUND(SUM(H5:H9)-SUM(H10:H16),2) -> 0 | I18: =ROUND(SUM(I5:I9)-SUM(I10:I16),2) -> 0 | J18: =ROUND(SUM(J5:J9)-SUM(J10:J16),2) -> 0 | ... M18: =ROUND(SUM(M5:M9)-SUM(M10:M16),2) -> 0

Sheet Despesas Gerais
B2: {=TRANSPOSE(Meses)} -> Janeiro | C2: Fevereiro | D2: Março | E2: Abril | F2: Maio | G2: Junho | H2: Julho | I2: Agosto | J2: Setembro | K2: Outubro | L2: Novembro | M2: Dezembro
A3: Receitas L. | B3: ='Receita Líquida'!B18 -> 0 | C3: ='Receita Líquida'!C18 -> 0 | D3: ='Receita Líquida'!D18 -> 0 | E3: ='Receita Líquida'!E18 -> 0 | F3: ='Receita Líquida'!F18 -> 0 | G3: ='Receita Líquida'!G18 -> 0 | H3: ='Receita Líquida'!H18 -> 0 | I3: ='Receita Líquida'!I18 -> 0 | ... M3: ='Receita Líquida'!M18 -> 0
A4: Saldo | B4: =B3-(SUM(B7:B18)) -> 0 | C4: =C3-(SUM(C7:C18))+B4 -> 0 | D4: =D3-(SUM(D7:D18))+C4 -> 0 | E4: =E3-(SUM(E7:E18))+D4 -> 0 | F4: =F3-(SUM(F7:F18))+E4 -> 0 | G4: =G3-(SUM(G7:G18))+F4 -> 0 | H4: =H3-(SUM(H7:H18))+G4 -> 0 | I4: =I3-(SUM(I7:I18))+H4 -> 0 | J4: =J3-(SUM(J7:J18))+I4 -> 0 | ... M4: =M3-(SUM(M7:M18))+L4 -> 0
A6: Descrição | B6: Valor | C6: Valor | D6: Valor | E6: Valor | F6: Valor | G6: Valor | H6: Valor | I6: Valor | J6: Valor | K6: Valor | L6: Valor | M6: Valor
A7: {=Despesas} -> Alimentação | B7: =SUMIFS(Tabela1[Valor],Tabela1[Mês],'Despesas Gerais'!B$2,Tabela1[Categoria],'Despesas Gerais'!$A7) -> 0 | C7: =SUMIFS(Tabela1[Valor],Tabela1[Mês],'Despesas Gerais'!C$2,Tabela1[Categoria],'Despesas Gerais'!$A7) -> 0 | D7: =SUMIFS(Tabela1[Valor],Tabela1[Mês],'Despesas Gerais'!D$2,Tabela1[Categoria],'Despesas Gerais'!$A7) -> 0 | E7: =SUMIFS(Tabela1[Valor],Tabela1[Mês],'Despesas Gerais'!E$2,Tabela1[Categoria],'Despesas Gerais'!$A7) -> 0 | F7: =SUMIFS(Tabela1[Valor],Tabela1[Mês],'Despesas Gerais'!F$2,Tabela1[Categoria],'Despesas Gerais'!$A7) -> 0 | G7: =SUMIFS(Tabela1[Valor],Tabela1[Mês],'Despesas Gerais'!G$2,Tabela1[Categoria],'Despesas Gerais'!$A7) -> 0 | H7: =SUMIFS(Tabela1[Valor],Tabela1[Mês],'Despesas Gerais'!H$2,Tabela1[Categoria],'Despesas Gerais'!$A7) -> 0 | I7: =SUMIFS(Tabela1[Valor],Tabela1[Mês],'Despesas Gerais'!I$2,Tabela1[Categoria],'Despesas Gerais'!$A7) -> 0 | ... M7: =SUMIFS(Tabela1[Valor],Tabela1[Mês],'Despesas Gerais'!M$2,Tabela1[Categoria],'Despesas Gerais'!$A7) -> 0
A8: Transp./ Carro | B8: =SUMIFS(Tabela1[Valor],Tabela1[Mês],'Despesas Gerais'!B$2,Tabela1[Categoria],'Despesas Gerais'!$A8) -> 0 | C8: =SUMIFS(Tabela1[Valor],Tabela1[Mês],'Despesas Gerais'!C$2,Tabela1[Categoria],'Despesas Gerais'!$A8) -> 0 | D8: =SUMIFS(Tabela1[Valor],Tabela1[Mês],'Despesas Gerais'!D$2,Tabela1[Categoria],'Despesas Gerais'!$A8) -> 0 | E8: =SUMIFS(Tabela1[Valor],Tabela1[Mês],'Despesas Gerais'!E$2,Tabela1[Categoria],'Despesas Gerais'!$A8) -> 0 | F8: =SUMIFS(Tabela1[Valor],Tabela1[Mês],'Despesas Gerais'!F$2,Tabela1[Categoria],'Despesas Gerais'!$A8) -> 0 | G8: =SUMIFS(Tabela1[Valor],Tabela1[Mês],'Despesas Gerais'!G$2,Tabela1[Categoria],'Despesas Gerais'!$A8) -> 0 | H8: =SUMIFS(Tabela1[Valor],Tabela1[Mês],'Despesas Gerais'!H$2,Tabela1[Categoria],'Despesas Gerais'!$A8) -> 0 | I8: =SUMIFS(Tabela1[Valor],Tabela1[Mês],'Despesas Gerais'!I$2,Tabela1[Categoria],'Despesas Gerais'!$A8) -> 0 | ... M8: =SUMIFS(Tabela1[Valor],Tabela1[Mês],'Despesas Gerais'!M$2,Tabela1[Categoria],'Despesas Gerais'!$A8) -> 0
A9: Condomínio | B9: =SUMIFS(Tabela1[Valor],Tabela1[Mês],'Despesas Gerais'!B$2,Tabela1[Categoria],'Despesas Gerais'!$A9) -> 0 | C9: =SUMIFS(Tabela1[Valor],Tabela1[Mês],'Despesas Gerais'!C$2,Tabela1[Categoria],'Despesas Gerais'!$A9) -> 0 | D9: =SUMIFS(Tabela1[Valor],Tabela1[Mês],'Despesas Gerais'!D$2,Tabela1[Categoria],'Despesas Gerais'!$A9) -> 0 | E9: =SUMIFS(Tabela1[Valor],Tabela1[Mês],'Despesas Gerais'!E$2,Tabela1[Categoria],'Despesas Gerais'!$A9) -> 0 | F9: =SUMIFS(Tabela1[Valor],Tabela1[Mês],'Despesas Gerais'!F$2,Tabela1[Categoria],'Despesas Gerais'!$A9) -> 0 | G9: =SUMIFS(Tabela1[Valor],Tabela1[Mês],'Despesas Gerais'!G$2,Tabela1[Categoria],'Despesas Gerais'!$A9) -> 0 | H9: =SUMIFS(Tabela1[Valor],Tabela1[Mês],'Despesas Gerais'!H$2,Tabela1[Categoria],'Despesas Gerais'!$A9) -> 0 | I9: =SUMIFS(Tabela1[Valor],Tabela1[Mês],'Despesas Gerais'!I$2,Tabela1[Categoria],'Despesas Gerais'!$A9) -> 0 | ... M9: =SUMIFS(Tabela1[Valor],Tabela1[Mês],'Despesas Gerais'!M$2,Tabela1[Categoria],'Despesas Gerais'!$A9) -> 0
A10: Curso | B10: =SUMIFS(Tabela1[Valor],Tabela1[Mês],'Despesas Gerais'!B$2,Tabela1[Categoria],'Despesas Gerais'!$A10) -> 0 | C10: =SUMIFS(Tabela1[Valor],Tabela1[Mês],'Despesas Gerais'!C$2,Tabela1[Categoria],'Despesas Gerais'!$A10) -> 0 | D10: =SUMIFS(Tabela1[Valor],Tabela1[Mês],'Despesas Gerais'!D$2,Tabela1[Categoria],'Despesas Gerais'!$A10) -> 0 | E10: =SUMIFS(Tabela1[Valor],Tabela1[Mês],'Despesas Gerais'!E$2,Tabela1[Categoria],'Despesas Gerais'!$A10) -> 0 | F10: =SUMIFS(Tabela1[Valor],Tabela1[Mês],'Despesas Gerais'!F$2,Tabela1[Categoria],'Despesas Gerais'!$A10) -> 0 | G10: =SUMIFS(Tabela1[Valor],Tabela1[Mês],'Despesas Gerais'!G$2,Tabela1[Categoria],'Despesas Gerais'!$A10) -> 0 | H10: =SUMIFS(Tabela1[Valor],Tabela1[Mês],'Despesas Gerais'!H$2,Tabela1[Categoria],'Despesas Gerais'!$A10) -> 0 | I10: =SUMIFS(Tabela1[Valor],Tabela1[Mês],'Despesas Gerais'!I$2,Tabela1[Categoria],'Despesas Gerais'!$A10) -> 0 | ... M10: =SUMIFS(Tabela1[Valor],Tabela1[Mês],'Despesas Gerais'!M$2,Tabela1[Categoria],'Despesas Gerais'!$A10) -> 0
A11: Eletrônicos | B11: =SUMIFS(Tabela1[Valor],Tabela1[Mês],'Despesas Gerais'!B$2,Tabela1[Categoria],'Despesas Gerais'!$A11) -> 0 | C11: =SUMIFS(Tabela1[Valor],Tabela1[Mês],'Despesas Gerais'!C$2,Tabela1[Categoria],'Despesas Gerais'!$A11) -> 0 | D11: =SUMIFS(Tabela1[Valor],Tabela1[Mês],'Despesas Gerais'!D$2,Tabela1[Categoria],'Despesas Gerais'!$A11) -> 0 | E11: =SUMIFS(Tabela1[Valor],Tabela1[Mês],'Despesas Gerais'!E$2,Tabela1[Categoria],'Despesas Gerais'!$A11) -> 0 | F11: =SUMIFS(Tabela1[Valor],Tabela1[Mês],'Despesas Gerais'!F$2,Tabela1[Categoria],'Despesas Gerais'!$A11) -> 0 | G11: =SUMIFS(Tabela1[Valor],Tabela1[Mês],'Despesas Gerais'!G$2,Tabela1[Categoria],'Despesas Gerais'!$A11) -> 0 | H11: =SUMIFS(Tabela1[Valor],Tabela1[Mês],'Despesas Gerais'!H$2,Tabela1[Categoria],'Despesas Gerais'!$A11) -> 0 | I11: =SUMIFS(Tabela1[Valor],Tabela1[Mês],'Despesas Gerais'!I$2,Tabela1[Categoria],'Despesas Gerais'!$A11) -> 0 | ... M11: =SUMIFS(Tabela1[Valor],Tabela1[Mês],'Despesas Gerais'!M$2,Tabela1[Categoria],'Despesas Gerais'!$A11) -> 0
A12: Farm. e Saúde. | B12: =SUMIFS(Tabela1[Valor],Tabela1[Mês],'Despesas Gerais'!B$2,Tabela1[Categoria],'Despesas Gerais'!$A12) -> 0 | C12: =SUMIFS(Tabela1[Valor],Tabela1[Mês],'Despesas Gerais'!C$2,Tabela1[Categoria],'Despesas Gerais'!$A12) -> 0 | D12: =SUMIFS(Tabela1[Valor],Tabela1[Mês],'Despesas Gerais'!D$2,Tabela1[Categoria],'Despesas Gerais'!$A12) -> 0 | E12: =SUMIFS(Tabela1[Valor],Tabela1[Mês],'Despesas Gerais'!E$2,Tabela1[Categoria],'Despesas Gerais'!$A12) -> 0 | F12: =SUMIFS(Tabela1[Valor],Tabela1[Mês],'Despesas Gerais'!F$2,Tabela1[Categoria],'Despesas Gerais'!$A12) -> 0 | G12: =SUMIFS(Tabela1[Valor],Tabela1[Mês],'Despesas Gerais'!G$2,Tabela1[Categoria],'Despesas Gerais'!$A12) -> 0 | H12: =SUMIFS(Tabela1[Valor],Tabela1[Mês],'Despesas Gerais'!H$2,Tabela1[Categoria],'Despesas Gerais'!$A12) -> 0 | I12: =SUMIFS(Tabela1[Valor],Tabela1[Mês],'Despesas Gerais'!I$2,Tabela1[Categoria],'Despesas Gerais'!$A12) -> 0 | ... M12: =SUMIFS(Tabela1[Valor],Tabela1[Mês],'Despesas Gerais'!M$2,Tabela1[Categoria],'Despesas Gerais'!$A12) -> 0
A13: G. Residencial | B13: =SUMIFS(Tabela1[Valor],Tabela1[Mês],'Despesas Gerais'!B$2,Tabela1[Categoria],'Despesas Gerais'!$A13) -> 0 | C13: =SUMIFS(Tabela1[Valor],Tabela1[Mês],'Despesas Gerais'!C$2,Tabela1[Categoria],'Despesas Gerais'!$A13) -> 0 | D13: =SUMIFS(Tabela1[Valor],Tabela1[Mês],'Despesas Gerais'!D$2,Tabela1[Categoria],'Despesas Gerais'!$A13) -> 0 | E13: =SUMIFS(Tabela1[Valor],Tabela1[Mês],'Despesas Gerais'!E$2,Tabela1[Categoria],'Despesas Gerais'!$A13) -> 0 | F13: =SUMIFS(Tabela1[Valor],Tabela1[Mês],'Despesas Gerais'!F$2,Tabela1[Categoria],'Despesas Gerais'!$A13) -> 0 | G13: =SUMIFS(Tabela1[Valor],Tabela1[Mês],'Despesas Gerais'!G$2,Tabela1[Categoria],'Despesas Gerais'!$A13) -> 0 | H13: =SUMIFS(Tabela1[Valor],Tabela1[Mês],'Despesas Gerais'!H$2,Tabela1[Categoria],'Despesas Gerais'!$A13) -> 0 | I13: =SUMIFS(Tabela1[Valor],Tabela1[Mês],'Despesas Gerais'!I$2,Tabela1[Categoria],'Despesas Gerais'!$A13) -> 0 | ... M13: =SUMIFS(Tabela1[Valor],Tabela1[Mês],'Despesas Gerais'!M$2,Tabela1[Categoria],'Despesas Gerais'!$A13) -> 0
A14: Gasolina | B14: =SUMIFS(Tabela1[Valor],Tabela1[Mês],'Despesas Gerais'!B$2,Tabela1[Categoria],'Despesas Gerais'!$A14) -> 0 | C14: =SUMIFS(Tabela1[Valor],Tabela1[Mês],'Despesas Gerais'!C$2,Tabela1[Categoria],'Despesas Gerais'!$A14) -> 0 | D14: =SUMIFS(Tabela1[Valor],Tabela1[Mês],'Despesas Gerais'!D$2,Tabela1[Categoria],'Despesas Gerais'!$A14) -> 0 | E14: =SUMIFS(Tabela1[Valor],Tabela1[Mês],'Despesas Gerais'!E$2,Tabela1[Categoria],'Despesas Gerais'!$A14) -> 0 | F14: =SUMIFS(Tabela1[Valor],Tabela1[Mês],'Despesas Gerais'!F$2,Tabela1[Categoria],'Despesas Gerais'!$A14) -> 0 | G14: =SUMIFS(Tabela1[Valor],Tabela1[Mês],'Despesas Gerais'!G$2,Tabela1[Categoria],'Despesas Gerais'!$A14) -> 0 | H14: =SUMIFS(Tabela1[Valor],Tabela1[Mês],'Despesas Gerais'!H$2,Tabela1[Categoria],'Despesas Gerais'!$A14) -> 0 | I14: =SUMIFS(Tabela1[Valor],Tabela1[Mês],'Despesas Gerais'!I$2,Tabela1[Categoria],'Despesas Gerais'!$A14) -> 0 | ... M14: =SUMIFS(Tabela1[Valor],Tabela1[Mês],'Despesas Gerais'!M$2,Tabela1[Categoria],'Despesas Gerais'!$A14) -> 0
A15: Jogos/ Livros | B15: =SUMIFS(Tabela1[Valor],Tabela1[Mês],'Despesas Gerais'!B$2,Tabela1[Categoria],'Despesas Gerais'!$A15) -> 0 | C15: =SUMIFS(Tabela1[Valor],Tabela1[Mês],'Despesas Gerais'!C$2,Tabela1[Categoria],'Despesas Gerais'!$A15) -> 0 | D15: =SUMIFS(Tabela1[Valor],Tabela1[Mês],'Despesas Gerais'!D$2,Tabela1[Categoria],'Despesas Gerais'!$A15) -> 0 | E15: =SUMIFS(Tabela1[Valor],Tabela1[Mês],'Despesas Gerais'!E$2,Tabela1[Categoria],'Despesas Gerais'!$A15) -> 0 | F15: =SUMIFS(Tabela1[Valor],Tabela1[Mês],'Despesas Gerais'!F$2,Tabela1[Categoria],'Despesas Gerais'!$A15) -> 0 | G15: =SUMIFS(Tabela1[Valor],Tabela1[Mês],'Despesas Gerais'!G$2,Tabela1[Categoria],'Despesas Gerais'!$A15) -> 0 | H15: =SUMIFS(Tabela1[Valor],Tabela1[Mês],'Despesas Gerais'!H$2,Tabela1[Categoria],'Despesas Gerais'!$A15) -> 0 | I15: =SUMIFS(Tabela1[Valor],Tabela1[Mês],'Despesas Gerais'!I$2,Tabela1[Categoria],'Despesas Gerais'!$A15) -> 0 | ... M15: =SUMIFS(Tabela1[Valor],Tabela1[Mês],'Despesas Gerais'!M$2,Tabela1[Categoria],'Despesas Gerais'!$A15) -> 0
A16: Rolê/ Entret. | B16: =SUMIFS(Tabela1[Valor],Tabela1[Mês],'Despesas Gerais'!B$2,Tabela1[Categoria],'Despesas Gerais'!$A16) -> 0 | C16: =SUMIFS(Tabela1[Valor],Tabela1[Mês],'Despesas Gerais'!C$2,Tabela1[Categoria],'Despesas Gerais'!$A16) -> 0 | D16: =SUMIFS(Tabela1[Valor],Tabela1[Mês],'Despesas Gerais'!D$2,Tabela1[Categoria],'Despesas Gerais'!$A16) -> 0 | E16: =SUMIFS(Tabela1[Valor],Tabela1[Mês],'Despesas Gerais'!E$2,Tabela1[Categoria],'Despesas Gerais'!$A16) -> 0 | F16: =SUMIFS(Tabela1[Valor],Tabela1[Mês],'Despesas Gerais'!F$2,Tabela1[Categoria],'Despesas Gerais'!$A16) -> 0 | G16: =SUMIFS(Tabela1[Valor],Tabela1[Mês],'Despesas Gerais'!G$2,Tabela1[Categoria],'Despesas Gerais'!$A16) -> 0 | H16: =SUMIFS(Tabela1[Valor],Tabela1[Mês],'Despesas Gerais'!H$2,Tabela1[Categoria],'Despesas Gerais'!$A16) -> 0 | I16: =SUMIFS(Tabela1[Valor],Tabela1[Mês],'Despesas Gerais'!I$2,Tabela1[Categoria],'Despesas Gerais'!$A16) -> 0 | ... M16: =SUMIFS(Tabela1[Valor],Tabela1[Mês],'Despesas Gerais'!M$2,Tabela1[Categoria],'Despesas Gerais'!$A16) -> 0
A17: Roupas | B17: =SUMIFS(Tabela1[Valor],Tabela1[Mês],'Despesas Gerais'!B$2,Tabela1[Categoria],'Despesas Gerais'!$A17) -> 0 | C17: =SUMIFS(Tabela1[Valor],Tabela1[Mês],'Despesas Gerais'!C$2,Tabela1[Categoria],'Despesas Gerais'!$A17) -> 0 | D17: =SUMIFS(Tabela1[Valor],Tabela1[Mês],'Despesas Gerais'!D$2,Tabela1[Categoria],'Despesas Gerais'!$A17) -> 0 | E17: =SUMIFS(Tabela1[Valor],Tabela1[Mês],'Despesas Gerais'!E$2,Tabela1[Categoria],'Despesas Gerais'!$A17) -> 0 | F17: =SUMIFS(Tabela1[Valor],Tabela1[Mês],'Despesas Gerais'!F$2,Tabela1[Categoria],'Despesas Gerais'!$A17) -> 0 | G17: =SUMIFS(Tabela1[Valor],Tabela1[Mês],'Despesas Gerais'!G$2,Tabela1[Categoria],'Despesas Gerais'!$A17) -> 0 | H17: =SUMIFS(Tabela1[Valor],Tabela1[Mês],'Despesas Gerais'!H$2,Tabela1[Categoria],'Despesas Gerais'!$A17) -> 0 | I17: =SUMIFS(Tabela1[Valor],Tabela1[Mês],'Despesas Gerais'!I$2,Tabela1[Categoria],'Despesas Gerais'!$A17) -> 0 | ... M17: =SUMIFS(Tabela1[Valor],Tabela1[Mês],'Despesas Gerais'!M$2,Tabela1[Categoria],'Despesas Gerais'!$A17) -> 0
A18: G. Gerais | B18: =SUMIFS(Tabela1[Valor],Tabela1[Mês],'Despesas Gerais'!B$2,Tabela1[Categoria],'Despesas Gerais'!$A18) -> 0 | C18: =SUMIFS(Tabela1[Valor],Tabela1[Mês],'Despesas Gerais'!C$2,Tabela1[Categoria],'Despesas Gerais'!$A18) -> 0 | D18: =SUMIFS(Tabela1[Valor],Tabela1[Mês],'Despesas Gerais'!D$2,Tabela1[Categoria],'Despesas Gerais'!$A18) -> 0 | E18: =SUMIFS(Tabela1[Valor],Tabela1[Mês],'Despesas Gerais'!E$2,Tabela1[Categoria],'Despesas Gerais'!$A18) -> 0 | F18: =SUMIFS(Tabela1[Valor],Tabela1[Mês],'Despesas Gerais'!F$2,Tabela1[Categoria],'Despesas Gerais'!$A18) -> 0 | G18: =SUMIFS(Tabela1[Valor],Tabela1[Mês],'Despesas Gerais'!G$2,Tabela1[Categoria],'Despesas Gerais'!$A18) -> 0 | H18: =SUMIFS(Tabela1[Valor],Tabela1[Mês],'Despesas Gerais'!H$2,Tabela1[Categoria],'Despesas Gerais'!$A18) -> 0 | I18: =SUMIFS(Tabela1[Valor],Tabela1[Mês],'Despesas Gerais'!I$2,Tabela1[Categoria],'Despesas Gerais'!$A18) -> 0 | ... M18: =SUMIFS(Tabela1[Valor],Tabela1[Mês],'Despesas Gerais'!M$2,Tabela1[Categoria],'Despesas Gerais'!$A18) -> 0
A20: Total | B20: =SUM(B7:B18) -> 0 | C20: =SUM(C7:C18) -> 0 | D20: =SUM(D7:D18) -> 0 | E20: =SUM(E7:E18) -> 0 | F20: =SUM(F7:F18) -> 0 | G20: =SUM(G7:G18) -> 0 | H20: =SUM(H7:H18) -> 0 | I20: =SUM(I7:I18) -> 0 | ... M20: =SUM(M7:M18) -> 0

Sheet Gráfico Anual
A2: Mês | C2: R. Líquida | D2: Investimentos | F2: Despesas | H2: Sld mês | I2: Sld. Atual | K2: Resultado - Total | N2: Despesas Fixas
A3: {=Meses} -> Janeiro | C3: ='Receita Líquida'!B18 -> 0 | D3: =SUM('Receita Líquida'!B$15:B$16) -> 0 | F3: =SUM('Despesas Gerais'!B20:B20) -> 0 | H3: =I3 -> 0 | I3: ='Despesas Gerais'!B4 -> 0 | K3: Receita Bruta | L3: =SUM('Receita Líquida'!B5:M9) -> 0 | N3: {=Despesas} -> Alimentação | O3: =SUM('Despesas Gerais'!B7:M7) -> 0
A4: Fevereiro | C4: ='Receita Líquida'!C18 -> 0 | D4: =SUM('Receita Líquida'!C$15:C$16) -> 0 | F4: =SUM('Despesas Gerais'!C20:C20) -> 0 | H4: =I4-I3 -> 0 | I4: ='Despesas Gerais'!C4 -> 0 | K4: Perdas | L4: =SUM('Receita Líquida'!B10:M14) -> 0 | N4: Transp./ Carro | O4: =SUM('Despesas Gerais'!B8:M8) -> 0
A5: Março | C5: ='Receita Líquida'!D18 -> 0 | D5: =SUM('Receita Líquida'!D$15:D$16) -> 0 | F5: =SUM('Despesas Gerais'!D20:D20) -> 0 | H5: =I5-I4 -> 0 | I5: ='Despesas Gerais'!D4 -> 0 | K5: Receita Líquida | L5: =SUM('Receita Líquida'!B18:M18) -> 0 | N5: Condomínio | O5: =SUM('Despesas Gerais'!B9:M9) -> 0
A6: Abril | C6: ='Receita Líquida'!E18 -> 0 | D6: =SUM('Receita Líquida'!E$15:E$16) -> 0 | F6: =SUM('Despesas Gerais'!E20:E20) -> 0 | H6: =I6-I5 -> 0 | I6: ='Despesas Gerais'!E4 -> 0 | K6: Desp. Fixas | L6: =SUM('Despesas Gerais'!B7:B17,'Despesas Gerais'!C7:C17,'Despesas Gerais'!D7:D17,'Despesas Gerais'!E7:E17,'Despesas Gerais'!F7:F17,'Despesas Gerais'!G7:G17,'Despesas Gerais'!H7:H17,'Despesas Gerais'!I7:I17,'Despesas Gerais'!J7:J17,'Despesas Gerais'!K7:K17,'Despesas Gerais'!L7:L17,'Despesas Gerais'!M7:M17) -> 0 | N6: Curso | O6: =SUM('Despesas Gerais'!B10:M10) -> 0
A7: Maio | C7: ='Receita Líquida'!F18 -> 0 | D7: =SUM('Receita Líquida'!F$15:F$16) -> 0 | F7: =SUM('Despesas Gerais'!F20:F20) -> 0 | H7: =I7-I6 -> 0 | I7: ='Despesas Gerais'!F4 -> 0 | K7: Desp. Gerais | L7: =SUM('Despesas Gerais'!B18:B18,'Despesas Gerais'!C18:C18,'Despesas Gerais'!D18:D18,'Despesas Gerais'!E18:E18,'Despesas Gerais'!F18:F18,'Despesas Gerais'!G18:G18,'Despesas Gerais'!H18:H18,'Despesas Gerais'!I18:I18,'Despesas Gerais'!J18:J18,'Despesas Gerais'!K18:K18,'Despesas Gerais'!L18:L18,'Despesas Gerais'!M18:M18) -> 0 | N7: Eletrônicos | O7: =SUM('Despesas Gerais'!B11:M11) -> 0
A8: Junho | C8: ='Receita Líquida'!G18 -> 0 | D8: =SUM('Receita Líquida'!G$15:G$16) -> 0 | F8: =SUM('Despesas Gerais'!G20:G20) -> 0 | H8: =I8-I7 -> 0 | I8: ='Despesas Gerais'!G4 -> 0 | K8: Desp. Total | L8: =SUM(L6:L7) -> 0 | N8: Farm. e Saúde. | O8: =SUM('Despesas Gerais'!B12:M12) -> 0
A9: Julho | C9: ='Receita Líquida'!H18 -> 0 | D9: =SUM('Receita Líquida'!H$15:H$16) -> 0 | F9: =SUM('Despesas Gerais'!H20:H20) -> 0 | H9: =I9-I8 -> 0 | I9: ='Despesas Gerais'!H4 -> 0 | K9: Saldo Anual | L9: ='Despesas Gerais'!M4 -> 0 | N9: G. Residencial | O9: =SUM('Despesas Gerais'!B13:M13) -> 0
A10: Agosto | C10: ='Receita Líquida'!I18 -> 0 | D10: =SUM('Receita Líquida'!I$15:I$16) -> 0 | F10: =SUM('Despesas Gerais'!I20:I20) -> 0 | H10: =I10-I9 -> 0 | I10: ='Despesas Gerais'!I4 -> 0 | K10: Investimento | L10: ='Gráfico Anual'!D15 -> 0 | N10: Gasolina | O10: =SUM('Despesas Gerais'!B14:M14) -> 0
A11: Setembro | C11: ='Receita Líquida'!J18 -> 0 | D11: =SUM('Receita Líquida'!J$15:J$16) -> 0 | F11: =SUM('Despesas Gerais'!J20:J20) -> 0 | H11: =I11-I10 -> 0 | I11: ='Despesas Gerais'!J4 -> 0 | N11: Jogos/ Livros | O11: =SUM('Despesas Gerais'!B15:M15) -> 0
A12: Outubro | C12: ='Receita Líquida'!K18 -> 0 | D12: =SUM('Receita Líquida'!K$15:K$16) -> 0 | F12: =SUM('Despesas Gerais'!K20:K20) -> 0 | H12: =I12-I11 -> 0 | I12: ='Despesas Gerais'!K4 -> 0 | N12: Rolê/ Entret. | O12: =SUM('Despesas Gerais'!B16:M16) -> 0
A13: Novembro | C13: ='Receita Líquida'!L18 -> 0 | D13: =SUM('Receita Líquida'!L$15:L$16) -> 0 | F13: =SUM('Despesas Gerais'!L20:L20) -> 0 | H13: =I13-I12 -> 0 | I13: ='Despesas Gerais'!L4 -> 0 | N13: Roupas | O13: =SUM('Despesas Gerais'!B17:M17) -> 0
A14: Dezembro | C14: ='Receita Líquida'!M18 -> 0 | D14: =SUM('Receita Líquida'!M$15:M$16) -> 0 | F14: =SUM('Despesas Gerais'!M20:N20) -> 0 | H14: =I14-I13 -> 0 | I14: ='Despesas Gerais'!M4 -> 0 | N14: G. Gerais | O14: =SUM('Despesas Gerais'!B18:M18) -> 0
A15: Total | C15: =SUM(C3:C14) -> 0 | D15: =SUM(D3:D14) -> 0 | F15: =SUM(F3:F14) -> 0 | H15: Saldo Anual | I15: ='Gráfico Anual'!L9 -> 0
A16: Média | C16: =AVERAGE(C3:C14) -> 0 | D16: =AVERAGE(D3:D14) -> 0 | F16: =AVERAGE(F3:F14) -> 0
A17: 1º Sem. | C17: =SUM(C3:C8) -> 0 | D17: =SUM(D3:D8) -> 0 | F17: =SUM(F3:F8) -> 0
A18: 2º Sem. | C18: =SUM($C$9:$C$14) -> 0 | D18: =SUM($D$9:$D$14) -> 0 | F18: =SUM($F$9:$F$14) -> 0

Sheet Análise
B2: Selecione - | E2: Intervalo | F2: Data | G2: Mês | H2: Operação | I2: Categoria | J2: Conta | K2: Valor | L2: Descrição
B3: Maior | C3: =MAX($K$3:$K$185) -> 0 | E3: 0 | F3: {=_xlfn._xlws.SORT(_xlfn._xlws.FILTER(Tabela1[],Tabela1[Descrição]=C2),1,1,FALSE)} -> 0 | H3: 0 | I3: 0 | J3: 0 | K3: 0 | L3: 0
B4: Menor | C4: =MIN($K$3:$K$185) -> 0 | E4: =IF(ISBLANK(F4),"",F4-F3) -> 0 | F4: 0 | H4: 0 | I4: 0 | J4: 0 | K4: 0 | L4: 0
B5: Média | C5: =AVERAGE($K$3:$K$185) -> 0 | E5: =IF(ISBLANK(F5),"",F5-F4)
B6: Totol | C6: =SUM($K$3:$K$185) -> 0 | E6: =IF(ISBLANK(F6),"",F6-F5)
B7: Quantidade | C7: =SUBTOTAL(2,F3:F185) -> 2 | E7: =IF(ISBLANK(F7),"",F7-F6)
B8: Próximo | C8: =IFERROR(AVERAGE($E$4:$E$185)+MAX($F$3:$F$185),"Não há dados.") -> 0 | E8: =IF(ISBLANK(F8),"",F8-F7)
E9: =IF(ISBLANK(F9),"",F9-F8)
B10: Mês | C10: Valor | E10: =IF(ISBLANK(F10),"",F10-F9)
B11: {=Meses} -> Janeiro | C11: =SUMIFS($K$3:$K$185,$G$3:$G$185,B11,$L$3:$L$185,$C$2) -> 0 | E11: =IF(ISBLANK(F11),"",F11-F10)
B12: Fevereiro | C12: =SUMIFS($K$3:$K$185,$G$3:$G$185,B12,$L$3:$L$185,$C$2) -> 0 | E12: =IF(ISBLANK(F12),"",F12-F11)
B13: Março | C13: =SUMIFS($K$3:$K$185,$G$3:$G$185,B13,$L$3:$L$185,$C$2) -> 0 | E13: =IF(ISBLANK(F13),"",F13-F12)
B14: Abril | C14: =SUMIFS($K$3:$K$185,$G$3:$G$185,B14,$L$3:$L$185,$C$2) -> 0 | E14: =IF(ISBLANK(F14),"",F14-F13)
B15: Maio | C15: =SUMIFS($K$3:$K$185,$G$3:$G$185,B15,$L$3:$L$185,$C$2) -> 0 | E15: =IF(ISBLANK(F15),"",F15-F14)
B16: Junho | C16: =SUMIFS($K$3:$K$185,$G$3:$G$185,B16,$L$3:$L$185,$C$2) -> 0 | E16: =IF(ISBLANK(F16),"",F16-F15)
B17: Julho | C17: =SUMIFS($K$3:$K$185,$G$3:$G$185,B17,$L$3:$L$185,$C$2) -> 0 | E17: =IF(ISBLANK(F17),"",F17-F16)
B18: Agosto | C18: =SUMIFS($K$3:$K$185,$G$3:$G$185,B18,$L$3:$L$185,$C$2) -> 0 | E18: =IF(ISBLANK(F18),"",F18-F17)
B19: Setembro | C19: =SUMIFS($K$3:$K$185,$G$3:$G$185,B19,$L$3:$L$185,$C$2) -> 0 | E19: =IF(ISBLANK(F19),"",F19-F18)
B20: Outubro | C20: =SUMIFS($K$3:$K$185,$G$3:$G$185,B20,$L$3:$L$185,$C$2) -> 0 | E20: =IF(ISBLANK(F20),"",F20-F19)
B21: Novembro | C21: =SUMIFS($K$3:$K$185,$G$3:$G$185,B21,$L$3:$L$185,$C$2) -> 0 | E21: =IF(ISBLANK(F21),"",F21-F20)
B22: Dezembro | C22: =SUMIFS($K$3:$K$185,$G$3:$G$185,B22,$L$3:$L$185,$C$2) -> 0 | E22: =IF(ISBLANK(F22),"",F22-F21)
E23: =IF(ISBLANK(F23),"",F23-F22)
E24: =IF(ISBLANK(F24),"",F24-F23)
E25: =IF(ISBLANK(F25),"",F25-F24)
E26: =IF(ISBLANK(F26),"",F26-F25)
E27: =IF(ISBLANK(F27),"",F27-F26)
E28: =IF(ISBLANK(F28),"",F28-F27)
E29: =IF(ISBLANK(F29),"",F29-F28)
E30: =IF(ISBLANK(F30),"",F30-F29)
E31: =IF(ISBLANK(F31),"",F31-F30)
E32: =IF(ISBLANK(F32),"",F32-F31)
E33: =IF(ISBLANK(F33),"",F33-F32)
E34: =IF(ISBLANK(F34),"",F34-F33)
... E185: =IF(ISBLANK(F185),"",F185-F184)
B201: =IF(ISBLANK(#REF!),"",C201-F185) -> 0
B202: =IF(ISBLANK(#REF!),"",C202-C201) -> 0
