Workbook
Name Accounts: Goals!#REF!
Name Accounts: 'Data Validation'!$B$5:$B$9
Name Dash: 'Graphic Annual'!$A$1:$P$26
Name Discount: Goals!#REF!
Name Discount: 'Data Validation'!$F$9:$F$13
Name Expenses: Goals!$D$5:$D$16
Name Expenses: 'Data Validation'!$D$5:$D$16
Name Income: Goals!#REF!
Name Income: 'Data Validation'!$H$5:$H$9
Name Investments: Goals!$E$5:$E$6
Name Investments: 'Data Validation'!$F$5:$F$6
Name Months: Goals!#REF!
Name Months: 'Data Validation'!$P$5:$P$16
Name Net_Salary: Goals!#REF!
Name Net_Salary: 'Data Validation'!$N$5:$N$16
Name Payment: 'Data Validation'!$J$5
Name Transfer: Goals!#REF!
Name Transfer: 'Data Validation'!$B$5:$B$8

Sheet Data Validation
B2: *Feel free to change the blue values as you wish. However, if you need to remove or add new values, you may need to adjust the spreadsheet accordingly.
B4: Accounts | D4: Expenses | F4: Investments | H4: Income | J4: Payment | L4: Transfer | N4: Net Salary | P4: Months
B5: Bank 1 | D5: Bills | F5: Stock Market | H5: Salary | J5: Credit Card | L5: {=Transfer} -> Bank 1 | N5: {=Income} -> Salary | P5: January
B6: Bank 2 | D6: Car | F6: Real Estate | H6: Seals | L6: Bank 2 | N6: Seals | P6: February
B7: Wallet | D7: Clothing | H7: Rent | L7: Wallet | N7: Rent | P7: March
B8: Savings | D8: Eletron n' games | F8: Discount | H8: Seals II | L8: Savings | N8: Seals II | P8: April
B9: Credit Card | D9: Food | F9: Tax I | H9: Other - Income | N9: Other - Income | P9: May
D10: Gasolina | F10: Tax II | N10: {=Discount} -> Tax I | P10: June
D11: Hang out | F11: Bank Fee I | N11: Tax II | P11: July
D12: Healthcare | F12: Bank Fee II | N12: Bank Fee I | P12: August
D13: Insurance | F13: Other - Discount | N13: Bank Fee II | P13: September
D14: Personal Care | N14: Other - Discount | P14: October
D15: Travel | N15: {=Investments} -> Stock Market | P15: November
D16: General expen. | N16: Real Estate | P16: December

Sheet Balance & Tracking
B2: January | C2: Total | E2: Description | F2: Amount
B3: Expenses | C3: =IF(B3="Expenses",HLOOKUP(B2,Expenses!B2:M20,19,FALSE),IF(B3="Net Salary",HLOOKUP(B2,'Net Salary'!B2:M16,15,FALSE),"")) -> 0 | E3: {=IF(B3="Expenses",Expenses,IF(B3="Net Salary",Net_Salary,""))} -> Bills | F3: {=IF(B3="Expenses",_xlfn._xlws.FILTER(Expenses!B7:M18,Expenses!B2:M2=B2),IF(B3="Net Salary",_xlfn._xlws.FILTER('Net Salary'!B3:M14,'Net Salary'!B2:M2=B2),""))} -> 0
B4: Debt/ Income | C4: =HLOOKUP(B2,Expenses!B2:M20,19,FALSE)/HLOOKUP(B2,'Net Salary'!B2:M16,15,FALSE) -> #DIV/0! | E4: Car | F4: 0
B5: Balance | C5: =VLOOKUP(B2,'Graphic Annual'!A3:I14,9,FALSE) -> 0 | E5: Clothing | F5: 0
B6: Annual Blc. | C6: ='Graphic Annual'!I15 -> 0 | E6: Eletron n' games | F6: 0
E7: Food | F7: 0
B8: Accounts | C8: Total | E8: Gasolina | F8: 0
B9: {=Accounts} -> Bank 1 | C9: {=SUM(SUMIFS(Tabela1[Amount],Tabela1[Operation],{"Income";"Transfer"},Tabela1[Account],B9,Tabela1[Date],"<="&(TODAY())))-SUMIFS(Tabela1[Amount],Tabela1[Operation],"<>Income",Tabela1[Operation],"<>Transfer",Tabela1[Account],B9,Tabela1[Date],"<="&(TODAY())) - SUMIFS(Tabela1[Amount],Tabela1[Category],B9,Tabela1[Date],"<="&(TODAY()))} -> 150 | E9: Hang out | F9: 0
B10: Bank 2 | C10: {=SUM(SUMIFS(Tabela1[Amount],Tabela1[Operation],{"Income";"Transfer"},Tabela1[Account],B10,Tabela1[Date],"<="&(TODAY())))-SUMIFS(Tabela1[Amount],Tabela1[Operation],"<>Income",Tabela1[Operation],"<>Transfer",Tabela1[Account],B10,Tabela1[Date],"<="&(TODAY())) - SUMIFS(Tabela1[Amount],Tabela1[Category],B10,Tabela1[Date],"<="&(TODAY()))} -> 0 | E10: Healthcare | F10: 0
B11: Wallet | C11: {=SUM(SUMIFS(Tabela1[Amount],Tabela1[Operation],{"Income";"Transfer"},Tabela1[Account],B11,Tabela1[Date],"<="&(TODAY())))-SUMIFS(Tabela1[Amount],Tabela1[Operation],"<>Income",Tabela1[Operation],"<>Transfer",Tabela1[Account],B11,Tabela1[Date],"<="&(TODAY())) - SUMIFS(Tabela1[Amount],Tabela1[Category],B11,Tabela1[Date],"<="&(TODAY()))} -> 0 | E11: Insurance | F11: 0
B12: Savings | C12: {=SUM(SUMIFS(Tabela1[Amount],Tabela1[Operation],{"Income";"Transfer"},Tabela1[Account],B12,Tabela1[Date],"<="&(TODAY())))-SUMIFS(Tabela1[Amount],Tabela1[Operation],"<>Income",Tabela1[Operation],"<>Transfer",Tabela1[Account],B12,Tabela1[Date],"<="&(TODAY())) - SUMIFS(Tabela1[Amount],Tabela1[Category],B12,Tabela1[Date],"<="&(TODAY()))} -> 0 | E12: Personal Care | F12: 0
B13: Credit Card | C13: =SUMIF(Tabela1[Account],B13,Tabela1[Amount])-SUMIFS(Tabela1[Amount],Tabela1[Category],B13,Tabela1[Date],"<="&(TODAY())) -> 0 | E13: Travel | F13: 0
B14: Difference | C14: =ROUND(C5-SUM(C9:C12),2) -> -150 | E14: General expen. | F14: 0
A16: =SUBTOTAL(2,Tabela1[Date]) -> 1 | B16: Date | C16: Month | D16: Operation | E16: Category | F16: Account | G16: Amount | H16: Description
B17: 45292 | C17: =IF(ISBLANK(B17),"",PROPER(TEXT(B17,"MMMM"))) -> Janeiro | D17: Income | E17: Salary | F17: Bank 1 | G17: 150
C18: =IF(ISBLANK(B18),"",PROPER(TEXT(B18,"MMMM")))
C19: =IF(ISBLANK(B19),"",PROPER(TEXT(B19,"MMMM")))
C20: =IF(ISBLANK(B20),"",PROPER(TEXT(B20,"MMMM")))
C248: =IF(ISBLANK(B248),"",PROPER(TEXT(B248,"MMMM")))
C249: =IF(ISBLANK(B249),"",PROPER(TEXT(B249,"MMMM")))
C258: =IF(ISBLANK(B258),"",PROPER(TEXT(B258,"MMMM"))) | D258: =IF(ISBLANK(C258),"",PROPER(TEXT(C258,"MMMM"))) | E258: =IF(ISBLANK(D258),"",PROPER(TEXT(D258,"MMMM"))) | F258: =IF(ISBLANK(E258),"",PROPER(TEXT(E258,"MMMM"))) | G258: =IF(ISBLANK(F258),"",PROPER(TEXT(F258,"MMMM")))
C267: =IF(ISBLANK(B267),"",PROPER(TEXT(B267,"MMMM")))
C268: =IF(ISBLANK(B268),"",PROPER(TEXT(B268,"MMMM")))
C269: =IF(ISBLANK(B269),"",PROPER(TEXT(B269,"MMMM")))
C270: =IF(ISBLANK(B270),"",PROPER(TEXT(B270,"MMMM")))
C271: =IF(ISBLANK(B271),"",PROPER(TEXT(B271,"MMMM")))
C272: =IF(ISBLANK(B272),"",PROPER(TEXT(B272,"MMMM")))
C273: =IF(ISBLANK(B273),"",PROPER(TEXT(B273,"MMMM")))
C274: =IF(ISBLANK(B274),"",PROPER(TEXT(B274,"MMMM")))
C275: =IF(ISBLANK(B275),"",PROPER(TEXT(B275,"MMMM")))
C276: =IF(ISBLANK(B276),"",PROPER(TEXT(B276,"MMMM")))
C277: =IF(ISBLANK(B277),"",PROPER(TEXT(B277,"MMMM")))
C278: =IF(ISBLANK(B278),"",PROPER(TEXT(B278,"MMMM")))
... C785: =IF(ISBLANK(B785),"",PROPER(TEXT(B785,"MMMM")))

Sheet Net Salary
B2: {=TRANSPOSE(Months)} -> January | C2: February | D2: March | E2: April | F2: May | G2: June | H2: July | I2: August | J2: September | K2: October | L2: November | M2: December
A3: {=Net_Salary} -> Salary | B3: =SUMIFS(Tabela1[Amount],Tabela1[Month],B$2,Tabela1[Category],$A3) -> 0 | C3: =SUMIFS(Tabela1[Amount],Tabela1[Month],C$2,Tabela1[Category],$A3) -> 0 | D3: =SUMIFS(Tabela1[Amount],Tabela1[Month],D$2,Tabela1[Category],$A3) -> 0 | E3: =SUMIFS(Tabela1[Amount],Tabela1[Month],E$2,Tabela1[Category],$A3) -> 0 | F3: =SUMIFS(Tabela1[Amount],Tabela1[Month],F$2,Tabela1[Category],$A3) -> 0 | G3: =SUMIFS(Tabela1[Amount],Tabela1[Month],G$2,Tabela1[Category],$A3) -> 0 | H3: =SUMIFS(Tabela1[Amount],Tabela1[Month],H$2,Tabela1[Category],$A3) -> 0 | I3: =SUMIFS(Tabela1[Amount],Tabela1[Month],I$2,Tabela1[Category],$A3) -> 0 | ... M3: =SUMIFS(Tabela1[Amount],Tabela1[Month],M$2,Tabela1[Category],$A3) -> 0
A4: Seals | B4: =SUMIFS(Tabela1[Amount],Tabela1[Month],B$2,Tabela1[Category],$A4) -> 0 | C4: =SUMIFS(Tabela1[Amount],Tabela1[Month],C$2,Tabela1[Category],$A4) -> 0 | D4: =SUMIFS(Tabela1[Amount],Tabela1[Month],D$2,Tabela1[Category],$A4) -> 0 | E4: =SUMIFS(Tabela1[Amount],Tabela1[Month],E$2,Tabela1[Category],$A4) -> 0 | F4: =SUMIFS(Tabela1[Amount],Tabela1[Month],F$2,Tabela1[Category],$A4) -> 0 | G4: =SUMIFS(Tabela1[Amount],Tabela1[Month],G$2,Tabela1[Category],$A4) -> 0 | H4: =SUMIFS(Tabela1[Amount],Tabela1[Month],H$2,Tabela1[Category],$A4) -> 0 | I4: =SUMIFS(Tabela1[Amount],Tabela1[Month],I$2,Tabela1[Category],$A4) -> 0 | ... M4: =SUMIFS(Tabela1[Amount],Tabela1[Month],M$2,Tabela1[Category],$A4) -> 0
A5: Rent | B5: =SUMIFS(Tabela1[Amount],Tabela1[Month],B$2,Tabela1[Category],$A5) -> 0 | C5: =SUMIFS(Tabela1[Amount],Tabela1[Month],C$2,Tabela1[Category],$A5) -> 0 | D5: =SUMIFS(Tabela1[Amount],Tabela1[Month],D$2,Tabela1[Category],$A5) -> 0 | E5: =SUMIFS(Tabela1[Amount],Tabela1[Month],E$2,Tabela1[Category],$A5) -> 0 | F5: =SUMIFS(Tabela1[Amount],Tabela1[Month],F$2,Tabela1[Category],$A5) -> 0 | G5: =SUMIFS(Tabela1[Amount],Tabela1[Month],G$2,Tabela1[Category],$A5) -> 0 | H5: =SUMIFS(Tabela1[Amount],Tabela1[Month],H$2,Tabela1[Category],$A5) -> 0 | I5: =SUMIFS(Tabela1[Amount],Tabela1[Month],I$2,Tabela1[Category],$A5) -> 0 | ... M5: =SUMIFS(Tabela1[Amount],Tabela1[Month],M$2,Tabela1[Category],$A5) -> 0
A6: Seals II | B6: =SUMIFS(Tabela1[Amount],Tabela1[Month],B$2,Tabela1[Category],$A6) -> 0 | C6: =SUMIFS(Tabela1[Amount],Tabela1[Month],C$2,Tabela1[Category],$A6) -> 0 | D6: =SUMIFS(Tabela1[Amount],Tabela1[Month],D$2,Tabela1[Category],$A6) -> 0 | E6: =SUMIFS(Tabela1[Amount],Tabela1[Month],E$2,Tabela1[Category],$A6) -> 0 | F6: =SUMIFS(Tabela1[Amount],Tabela1[Month],F$2,Tabela1[Category],$A6) -> 0 | G6: =SUMIFS(Tabela1[Amount],Tabela1[Month],G$2,Tabela1[Category],$A6) -> 0 | H6: =SUMIFS(Tabela1[Amount],Tabela1[Month],H$2,Tabela1[Category],$A6) -> 0 | I6: =SUMIFS(Tabela1[Amount],Tabela1[Month],I$2,Tabela1[Category],$A6) -> 0 | ... M6: =SUMIFS(Tabela1[Amount],Tabela1[Month],M$2,Tabela1[Category],$A6) -> 0
A7: Other - Income | B7: =SUMIFS(Tabela1[Amount],Tabela1[Month],B$2,Tabela1[Category],$A7) -> 0 | C7: =SUMIFS(Tabela1[Amount],Tabela1[Month],C$2,Tabela1[Category],$A7) -> 0 | D7: =SUMIFS(Tabela1[Amount],Tabela1[Month],D$2,Tabela1[Category],$A7) -> 0 | E7: =SUMIFS(Tabela1[Amount],Tabela1[Month],E$2,Tabela1[Category],$A7) -> 0 | F7: =SUMIFS(Tabela1[Amount],Tabela1[Month],F$2,Tabela1[Category],$A7) -> 0 | G7: =SUMIFS(Tabela1[Amount],Tabela1[Month],G$2,Tabela1[Category],$A7) -> 0 | H7: =SUMIFS(Tabela1[Amount],Tabela1[Month],H$2,Tabela1[Category],$A7) -> 0 | I7: =SUMIFS(Tabela1[Amount],Tabela1[Month],I$2,Tabela1[Category],$A7) -> 0 | ... M7: =SUMIFS(Tabela1[Amount],Tabela1[Month],M$2,Tabela1[Category],$A7) -> 0
A8: Tax I | B8: =SUMIFS(Tabela1[Amount],Tabela1[Month],B$2,Tabela1[Category],$A8) -> 0 | C8: =SUMIFS(Tabela1[Amount],Tabela1[Month],C$2,Tabela1[Category],$A8) -> 0 | D8: =SUMIFS(Tabela1[Amount],Tabela1[Month],D$2,Tabela1[Category],$A8) -> 0 | E8: =SUMIFS(Tabela1[Amount],Tabela1[Month],E$2,Tabela1[Category],$A8) -> 0 | F8: =SUMIFS(Tabela1[Amount],Tabela1[Month],F$2,Tabela1[Category],$A8) -> 0 | G8: =SUMIFS(Tabela1[Amount],Tabela1[Month],G$2,Tabela1[Category],$A8) -> 0 | H8: =SUMIFS(Tabela1[Amount],Tabela1[Month],H$2,Tabela1[Category],$A8) -> 0 | I8: =SUMIFS(Tabela1[Amount],Tabela1[Month],I$2,Tabela1[Category],$A8) -> 0 | ... M8: =SUMIFS(Tabela1[Amount],Tabela1[Month],M$2,Tabela1[Category],$A8) -> 0
A9: Tax II | B9: =SUMIFS(Tabela1[Amount],Tabela1[Month],B$2,Tabela1[Category],$A9) -> 0 | C9: =SUMIFS(Tabela1[Amount],Tabela1[Month],C$2,Tabela1[Category],$A9) -> 0 | D9: =SUMIFS(Tabela1[Amount],Tabela1[Month],D$2,Tabela1[Category],$A9) -> 0 | E9: =SUMIFS(Tabela1[Amount],Tabela1[Month],E$2,Tabela1[Category],$A9) -> 0 | F9: =SUMIFS(Tabela1[Amount],Tabela1[Month],F$2,Tabela1[Category],$A9) -> 0 | G9: =SUMIFS(Tabela1[Amount],Tabela1[Month],G$2,Tabela1[Category],$A9) -> 0 | H9: =SUMIFS(Tabela1[Amount],Tabela1[Month],H$2,Tabela1[Category],$A9) -> 0 | I9: =SUMIFS(Tabela1[Amount],Tabela1[Month],I$2,Tabela1[Category],$A9) -> 0 | ... M9: =SUMIFS(Tabela1[Amount],Tabela1[Month],M$2,Tabela1[Category],$A9) -> 0
A10: Bank Fee I | B10: =SUMIFS(Tabela1[Amount],Tabela1[Month],B$2,Tabela1[Category],$A10) -> 0 | C10: =SUMIFS(Tabela1[Amount],Tabela1[Month],C$2,Tabela1[Category],$A10) -> 0 | D10: =SUMIFS(Tabela1[Amount],Tabela1[Month],D$2,Tabela1[Category],$A10) -> 0 | E10: =SUMIFS(Tabela1[Amount],Tabela1[Month],E$2,Tabela1[Category],$A10) -> 0 | F10: =SUMIFS(Tabela1[Amount],Tabela1[Month],F$2,Tabela1[Category],$A10) -> 0 | G10: =SUMIFS(Tabela1[Amount],Tabela1[Month],G$2,Tabela1[Category],$A10) -> 0 | H10: =SUMIFS(Tabela1[Amount],Tabela1[Month],H$2,Tabela1[Category],$A10) -> 0 | I10: =SUMIFS(Tabela1[Amount],Tabela1[Month],I$2,Tabela1[Category],$A10) -> 0 | ... M10: =SUMIFS(Tabela1[Amount],Tabela1[Month],M$2,Tabela1[Category],$A10) -> 0
A11: Bank Fee II | B11: =SUMIFS(Tabela1[Amount],Tabela1[Month],B$2,Tabela1[Category],$A11) -> 0 | C11: =SUMIFS(Tabela1[Amount],Tabela1[Month],C$2,Tabela1[Category],$A11) -> 0 | D11: =SUMIFS(Tabela1[Amount],Tabela1[Month],D$2,Tabela1[Category],$A11) -> 0 | E11: =SUMIFS(Tabela1[Amount],Tabela1[Month],E$2,Tabela1[Category],$A11) -> 0 | F11: =SUMIFS(Tabela1[Amount],Tabela1[Month],F$2,Tabela1[Category],$A11) -> 0 | G11: =SUMIFS(Tabela1[Amount],Tabela1[Month],G$2,Tabela1[Category],$A11) -> 0 | H11: =SUMIFS(Tabela1[Amount],Tabela1[Month],H$2,Tabela1[Category],$A11) -> 0 | I11: =SUMIFS(Tabela1[Amount],Tabela1[Month],I$2,Tabela1[Category],$A11) -> 0 | ... M11: =SUMIFS(Tabela1[Amount],Tabela1[Month],M$2,Tabela1[Category],$A11) -> 0
A12: Other - Discount | B12: =SUMIFS(Tabela1[Amount],Tabela1[Month],B$2,Tabela1[Category],$A12) -> 0 | C12: =SUMIFS(Tabela1[Amount],Tabela1[Month],C$2,Tabela1[Category],$A12) -> 0 | D12: =SUMIFS(Tabela1[Amount],Tabela1[Month],D$2,Tabela1[Category],$A12) -> 0 | E12: =SUMIFS(Tabela1[Amount],Tabela1[Month],E$2,Tabela1[Category],$A12) -> 0 | F12: =SUMIFS(Tabela1[Amount],Tabela1[Month],F$2,Tabela1[Category],$A12) -> 0 | G12: =SUMIFS(Tabela1[Amount],Tabela1[Month],G$2,Tabela1[Category],$A12) -> 0 | H12: =SUMIFS(Tabela1[Amount],Tabela1[Month],H$2,Tabela1[Category],$A12) -> 0 | I12: =SUMIFS(Tabela1[Amount],Tabela1[Month],I$2,Tabela1[Category],$A12) -> 0 | ... M12: =SUMIFS(Tabela1[Amount],Tabela1[Month],M$2,Tabela1[Category],$A12) -> 0
A13: Stock Market | B13: =SUMIFS(Tabela1[Amount],Tabela1[Month],B$2,Tabela1[Category],$A13) -> 0 | C13: =SUMIFS(Tabela1[Amount],Tabela1[Month],C$2,Tabela1[Category],$A13) -> 0 | D13: =SUMIFS(Tabela1[Amount],Tabela1[Month],D$2,Tabela1[Category],$A13) -> 0 | E13: =SUMIFS(Tabela1[Amount],Tabela1[Month],E$2,Tabela1[Category],$A13) -> 0 | F13: =SUMIFS(Tabela1[Amount],Tabela1[Month],F$2,Tabela1[Category],$A13) -> 0 | G13: =SUMIFS(Tabela1[Amount],Tabela1[Month],G$2,Tabela1[Category],$A13) -> 0 | H13: =SUMIFS(Tabela1[Amount],Tabela1[Month],H$2,Tabela1[Category],$A13) -> 0 | I13: =SUMIFS(Tabela1[Amount],Tabela1[Month],I$2,Tabela1[Category],$A13) -> 0 | ... M13: =SUMIFS(Tabela1[Amount],Tabela1[Month],M$2,Tabela1[Category],$A13) -> 0
A14: Real Estate | B14: =SUMIFS(Tabela1[Amount],Tabela1[Month],B$2,Tabela1[Category],$A14) -> 0 | C14: =SUMIFS(Tabela1[Amount],Tabela1[Month],C$2,Tabela1[Category],$A14) -> 0 | D14: =SUMIFS(Tabela1[Amount],Tabela1[Month],D$2,Tabela1[Category],$A14) -> 0 | E14: =SUMIFS(Tabela1[Amount],Tabela1[Month],E$2,Tabela1[Category],$A14) -> 0 | F14: =SUMIFS(Tabela1[Amount],Tabela1[Month],F$2,Tabela1[Category],$A14) -> 0 | G14: =SUMIFS(Tabela1[Amount],Tabela1[Month],G$2,Tabela1[Category],$A14) -> 0 | H14: =SUMIFS(Tabela1[Amount],Tabela1[Month],H$2,Tabela1[Category],$A14) -> 0 | I14: =SUMIFS(Tabela1[Amount],Tabela1[Month],I$2,Tabela1[Category],$A14) -> 0 | ... M14: =SUMIFS(Tabela1[Amount],Tabela1[Month],M$2,Tabela1[Category],$A14) -> 0
A16: Total | B16: =ROUND(SUM(B3:B7)-SUM(B8:B14),2) -> 0 | C16: =ROUND(SUM(C3:C7)-SUM(C8:C14),2) -> 0 | D16: =ROUND(SUM(D3:D7)-SUM(D8:D14),2) -> 0 | E16: =ROUND(SUM(E3:E7)-SUM(E8:E14),2) -> 0 | F16: =ROUND(SUM(F3:F7)-SUM(F8:F14),2) -> 0 | G16: =ROUND(SUM(G3:G7)-SUM(G8:G14),2) -> 0 | H16: =ROUND(SUM(H3:H7)-SUM(H8:H14),2) -> 0 | I16: =ROUND(SUM(I3:I7)-SUM(I8:I14),2) -> 0 | ... M16: =ROUND(SUM(M3:M7)-SUM(M8:M14),2) -> 0
A18: =A10 -> Bank Fee I | B18: =ROUND(IF((SUM(B3:B7) - SUM(B8:B9,B11:B12)) > 10, (SUM(B3:B7) - SUM(B8:B9,B11:B12))*0.1, )-B10,2) -> 0 | C18: =ROUND(IF((SUM(C3:C7) - SUM(C8:C9,C11:C12)) > 10, (SUM(C3:C7) - SUM(C8:C9,C11:C12))*0.1, )-C10,2) -> 0 | D18: =ROUND(IF((SUM(D3:D7) - SUM(D8:D9,D11:D12)) > 10, (SUM(D3:D7) - SUM(D8:D9,D11:D12))*0.1, )-D10,2) -> 0 | E18: =ROUND(IF((SUM(E3:E7) - SUM(E8:E9,E11:E12)) > 10, (SUM(E3:E7) - SUM(E8:E9,E11:E12))*0.1, )-E10,2) -> 0 | F18: =ROUND(IF((SUM(F3:F7) - SUM(F8:F9,F11:F12)) > 10, (SUM(F3:F7) - SUM(F8:F9,F11:F12))*0.1, )-F10,2) -> 0 | G18: =ROUND(IF((SUM(G3:G7) - SUM(G8:G9,G11:G12)) > 10, (SUM(G3:G7) - SUM(G8:G9,G11:G12))*0.1, )-G10,2) -> 0 | H18: =ROUND(IF((SUM(H3:H7) - SUM(H8:H9,H11:H12)) > 10, (SUM(H3:H7) - SUM(H8:H9,H11:H12))*0.1, )-H10,2) -> 0 | I18: =ROUND(IF((SUM(I3:I7) - SUM(I8:I9,I11:I12)) > 10, (SUM(I3:I7) - SUM(I8:I9,I11:I12))*0.1, )-I10,2) -> 0 | ... M18: =ROUND(IF((SUM(M3:M7) - SUM(M8:M9,M11:M12)) > 10, (SUM(M3:M7) - SUM(M8:M9,M11:M12))*0.1, )-M10,2) -> 0

Sheet Expenses
B2: {=TRANSPOSE(Months)} -> January | C2: February | D2: March | E2: April | F2: May | G2: June | H2: July | I2: August | J2: September | K2: October | L2: November | M2: December
A3: Net Salary | B3: ='Net Salary'!B16 -> 0 | C3: ='Net Salary'!C16 -> 0 | D3: ='Net Salary'!D16 -> 0 | E3: ='Net Salary'!E16 -> 0 | F3: ='Net Salary'!F16 -> 0 | G3: ='Net Salary'!G16 -> 0 | H3: ='Net Salary'!H16 -> 0 | I3: ='Net Salary'!I16 -> 0 | ... M3: ='Net Salary'!M16 -> 0
A4: Balance | B4: =B3-(SUM(B7:B18)) -> 0 | C4: =C3-(SUM(C7:C18))+B4 -> 0 | D4: =D3-(SUM(D7:D18))+C4 -> 0 | E4: =E3-(SUM(E7:E18))+D4 -> 0 | F4: =F3-(SUM(F7:F18))+E4 -> 0 | G4: =G3-(SUM(G7:G18))+F4 -> 0 | H4: =H3-(SUM(H7:H18))+G4 -> 0 | I4: =I3-(SUM(I7:I18))+H4 -> 0 | J4: =J3-(SUM(J7:J18))+I4 -> 0 | ... L4: =L3-(SUM(L7:L18))+K4 -> 0 | M4: =M3-SUM(M7:M18)+L4 -> 0
A6: Description | B6: Amount | C6: Amount | D6: Amount | E6: Amount | F6: Amount | G6: Amount | H6: Amount | I6: Amount | J6: Amount | K6: Amount | L6: Amount | M6: Amount
A7: {=Expenses} -> Bills | B7: =SUMIFS(Tabela1[Amount],Tabela1[Month],Expenses!B$2,Tabela1[Category],Expenses!$A7) -> 0 | C7: =SUMIFS(Tabela1[Amount],Tabela1[Month],Expenses!C$2,Tabela1[Category],Expenses!$A7) -> 0 | D7: =SUMIFS(Tabela1[Amount],Tabela1[Month],Expenses!D$2,Tabela1[Category],Expenses!$A7) -> 0 | E7: =SUMIFS(Tabela1[Amount],Tabela1[Month],Expenses!E$2,Tabela1[Category],Expenses!$A7) -> 0 | F7: =SUMIFS(Tabela1[Amount],Tabela1[Month],Expenses!F$2,Tabela1[Category],Expenses!$A7) -> 0 | G7: =SUMIFS(Tabela1[Amount],Tabela1[Month],Expenses!G$2,Tabela1[Category],Expenses!$A7) -> 0 | H7: =SUMIFS(Tabela1[Amount],Tabela1[Month],Expenses!H$2,Tabela1[Category],Expenses!$A7) -> 0 | I7: =SUMIFS(Tabela1[Amount],Tabela1[Month],Expenses!I$2,Tabela1[Category],Expenses!$A7) -> 0 | ... M7: =SUMIFS(Tabela1[Amount],Tabela1[Month],Expenses!M$2,Tabela1[Category],Expenses!$A7) -> 0
A8: Car | B8: =SUMIFS(Tabela1[Amount],Tabela1[Month],Expenses!B$2,Tabela1[Category],Expenses!$A8) -> 0 | C8: =SUMIFS(Tabela1[Amount],Tabela1[Month],Expenses!C$2,Tabela1[Category],Expenses!$A8) -> 0 | D8: =SUMIFS(Tabela1[Amount],Tabela1[Month],Expenses!D$2,Tabela1[Category],Expenses!$A8) -> 0 | E8: =SUMIFS(Tabela1[Amount],Tabela1[Month],Expenses!E$2,Tabela1[Category],Expenses!$A8) -> 0 | F8: =SUMIFS(Tabela1[Amount],Tabela1[Month],Expenses!F$2,Tabela1[Category],Expenses!$A8) -> 0 | G8: =SUMIFS(Tabela1[Amount],Tabela1[Month],Expenses!G$2,Tabela1[Category],Expenses!$A8) -> 0 | H8: =SUMIFS(Tabela1[Amount],Tabela1[Month],Expenses!H$2,Tabela1[Category],Expenses!$A8) -> 0 | I8: =SUMIFS(Tabela1[Amount],Tabela1[Month],Expenses!I$2,Tabela1[Category],Expenses!$A8) -> 0 | ... M8: =SUMIFS(Tabela1[Amount],Tabela1[Month],Expenses!M$2,Tabela1[Category],Expenses!$A8) -> 0
A9: Clothing | B9: =SUMIFS(Tabela1[Amount],Tabela1[Month],Expenses!B$2,Tabela1[Category],Expenses!$A9) -> 0 | C9: =SUMIFS(Tabela1[Amount],Tabela1[Month],Expenses!C$2,Tabela1[Category],Expenses!$A9) -> 0 | D9: =SUMIFS(Tabela1[Amount],Tabela1[Month],Expenses!D$2,Tabela1[Category],Expenses!$A9) -> 0 | E9: =SUMIFS(Tabela1[Amount],Tabela1[Month],Expenses!E$2,Tabela1[Category],Expenses!$A9) -> 0 | F9: =SUMIFS(Tabela1[Amount],Tabela1[Month],Expenses!F$2,Tabela1[Category],Expenses!$A9) -> 0 | G9: =SUMIFS(Tabela1[Amount],Tabela1[Month],Expenses!G$2,Tabela1[Category],Expenses!$A9) -> 0 | H9: =SUMIFS(Tabela1[Amount],Tabela1[Month],Expenses!H$2,Tabela1[Category],Expenses!$A9) -> 0 | I9: =SUMIFS(Tabela1[Amount],Tabela1[Month],Expenses!I$2,Tabela1[Category],Expenses!$A9) -> 0 | ... M9: =SUMIFS(Tabela1[Amount],Tabela1[Month],Expenses!M$2,Tabela1[Category],Expenses!$A9) -> 0
A10: Eletron n' games | B10: =SUMIFS(Tabela1[Amount],Tabela1[Month],Expenses!B$2,Tabela1[Category],Expenses!$A10) -> 0 | C10: =SUMIFS(Tabela1[Amount],Tabela1[Month],Expenses!C$2,Tabela1[Category],Expenses!$A10) -> 0 | D10: =SUMIFS(Tabela1[Amount],Tabela1[Month],Expenses!D$2,Tabela1[Category],Expenses!$A10) -> 0 | E10: =SUMIFS(Tabela1[Amount],Tabela1[Month],Expenses!E$2,Tabela1[Category],Expenses!$A10) -> 0 | F10: =SUMIFS(Tabela1[Amount],Tabela1[Month],Expenses!F$2,Tabela1[Category],Expenses!$A10) -> 0 | G10: =SUMIFS(Tabela1[Amount],Tabela1[Month],Expenses!G$2,Tabela1[Category],Expenses!$A10) -> 0 | H10: =SUMIFS(Tabela1[Amount],Tabela1[Month],Expenses!H$2,Tabela1[Category],Expenses!$A10) -> 0 | I10: =SUMIFS(Tabela1[Amount],Tabela1[Month],Expenses!I$2,Tabela1[Category],Expenses!$A10) -> 0 | ... M10: =SUMIFS(Tabela1[Amount],Tabela1[Month],Expenses!M$2,Tabela1[Category],Expenses!$A10) -> 0
A11: Food | B11: =SUMIFS(Tabela1[Amount],Tabela1[Month],Expenses!B$2,Tabela1[Category],Expenses!$A11) -> 0 | C11: =SUMIFS(Tabela1[Amount],Tabela1[Month],Expenses!C$2,Tabela1[Category],Expenses!$A11) -> 0 | D11: =SUMIFS(Tabela1[Amount],Tabela1[Month],Expenses!D$2,Tabela1[Category],Expenses!$A11) -> 0 | E11: =SUMIFS(Tabela1[Amount],Tabela1[Month],Expenses!E$2,Tabela1[Category],Expenses!$A11) -> 0 | F11: =SUMIFS(Tabela1[Amount],Tabela1[Month],Expenses!F$2,Tabela1[Category],Expenses!$A11) -> 0 | G11: =SUMIFS(Tabela1[Amount],Tabela1[Month],Expenses!G$2,Tabela1[Category],Expenses!$A11) -> 0 | H11: =SUMIFS(Tabela1[Amount],Tabela1[Month],Expenses!H$2,Tabela1[Category],Expenses!$A11) -> 0 | I11: =SUMIFS(Tabela1[Amount],Tabela1[Month],Expenses!I$2,Tabela1[Category],Expenses!$A11) -> 0 | ... M11: =SUMIFS(Tabela1[Amount],Tabela1[Month],Expenses!M$2,Tabela1[Category],Expenses!$A11) -> 0
A12: Gasolina | B12: =SUMIFS(Tabela1[Amount],Tabela1[Month],Expenses!B$2,Tabela1[Category],Expenses!$A12) -> 0 | C12: =SUMIFS(Tabela1[Amount],Tabela1[Month],Expenses!C$2,Tabela1[Category],Expenses!$A12) -> 0 | D12: =SUMIFS(Tabela1[Amount],Tabela1[Month],Expenses!D$2,Tabela1[Category],Expenses!$A12) -> 0 | E12: =SUMIFS(Tabela1[Amount],Tabela1[Month],Expenses!E$2,Tabela1[Category],Expenses!$A12) -> 0 | F12: =SUMIFS(Tabela1[Amount],Tabela1[Month],Expenses!F$2,Tabela1[Category],Expenses!$A12) -> 0 | G12: =SUMIFS(Tabela1[Amount],Tabela1[Month],Expenses!G$2,Tabela1[Category],Expenses!$A12) -> 0 | H12: =SUMIFS(Tabela1[Amount],Tabela1[Month],Expenses!H$2,Tabela1[Category],Expenses!$A12) -> 0 | I12: =SUMIFS(Tabela1[Amount],Tabela1[Month],Expenses!I$2,Tabela1[Category],Expenses!$A12) -> 0 | ... M12: =SUMIFS(Tabela1[Amount],Tabela1[Month],Expenses!M$2,Tabela1[Category],Expenses!$A12) -> 0
A13: Hang out | B13: =SUMIFS(Tabela1[Amount],Tabela1[Month],Expenses!B$2,Tabela1[Category],Expenses!$A13) -> 0 | C13: =SUMIFS(Tabela1[Amount],Tabela1[Month],Expenses!C$2,Tabela1[Category],Expenses!$A13) -> 0 | D13: =SUMIFS(Tabela1[Amount],Tabela1[Month],Expenses!D$2,Tabela1[Category],Expenses!$A13) -> 0 | E13: =SUMIFS(Tabela1[Amount],Tabela1[Month],Expenses!E$2,Tabela1[Category],Expenses!$A13) -> 0 | F13: =SUMIFS(Tabela1[Amount],Tabela1[Month],Expenses!F$2,Tabela1[Category],Expenses!$A13) -> 0 | G13: =SUMIFS(Tabela1[Amount],Tabela1[Month],Expenses!G$2,Tabela1[Category],Expenses!$A13) -> 0 | H13: =SUMIFS(Tabela1[Amount],Tabela1[Month],Expenses!H$2,Tabela1[Category],Expenses!$A13) -> 0 | I13: =SUMIFS(Tabela1[Amount],Tabela1[Month],Expenses!I$2,Tabela1[Category],Expenses!$A13) -> 0 | ... M13: =SUMIFS(Tabela1[Amount],Tabela1[Month],Expenses!M$2,Tabela1[Category],Expenses!$A13) -> 0
A14: Healthcare | B14: =SUMIFS(Tabela1[Amount],Tabela1[Month],Expenses!B$2,Tabela1[Category],Expenses!$A14) -> 0 | C14: =SUMIFS(Tabela1[Amount],Tabela1[Month],Expenses!C$2,Tabela1[Category],Expenses!$A14) -> 0 | D14: =SUMIFS(Tabela1[Amount],Tabela1[Month],Expenses!D$2,Tabela1[Category],Expenses!$A14) -> 0 | E14: =SUMIFS(Tabela1[Amount],Tabela1[Month],Expenses!E$2,Tabela1[Category],Expenses!$A14) -> 0 | F14: =SUMIFS(Tabela1[Amount],Tabela1[Month],Expenses!F$2,Tabela1[Category],Expenses!$A14) -> 0 | G14: =SUMIFS(Tabela1[Amount],Tabela1[Month],Expenses!G$2,Tabela1[Category],Expenses!$A14) -> 0 | H14: =SUMIFS(Tabela1[Amount],Tabela1[Month],Expenses!H$2,Tabela1[Category],Expenses!$A14) -> 0 | I14: =SUMIFS(Tabela1[Amount],Tabela1[Month],Expenses!I$2,Tabela1[Category],Expenses!$A14) -> 0 | ... M14: =SUMIFS(Tabela1[Amount],Tabela1[Month],Expenses!M$2,Tabela1[Category],Expenses!$A14) -> 0
A15: Insurance | B15: =SUMIFS(Tabela1[Amount],Tabela1[Month],Expenses!B$2,Tabela1[Category],Expenses!$A15) -> 0 | C15: =SUMIFS(Tabela1[Amount],Tabela1[Month],Expenses!C$2,Tabela1[Category],Expenses!$A15) -> 0 | D15: =SUMIFS(Tabela1[Amount],Tabela1[Month],Expenses!D$2,Tabela1[Category],Expenses!$A15) -> 0 | E15: =SUMIFS(Tabela1[Amount],Tabela1[Month],Expenses!E$2,Tabela1[Category],Expenses!$A15) -> 0 | F15: =SUMIFS(Tabela1[Amount],Tabela1[Month],Expenses!F$2,Tabela1[Category],Expenses!$A15) -> 0 | G15: =SUMIFS(Tabela1[Amount],Tabela1[Month],Expenses!G$2,Tabela1[Category],Expenses!$A15) -> 0 | H15: =SUMIFS(Tabela1[Amount],Tabela1[Month],Expenses!H$2,Tabela1[Category],Expenses!$A15) -> 0 | I15: =SUMIFS(Tabela1[Amount],Tabela1[Month],Expenses!I$2,Tabela1[Category],Expenses!$A15) -> 0 | ... M15: =SUMIFS(Tabela1[Amount],Tabela1[Month],Expenses!M$2,Tabela1[Category],Expenses!$A15) -> 0
A16: Personal Care | B16: =SUMIFS(Tabela1[Amount],Tabela1[Month],Expenses!B$2,Tabela1[Category],Expenses!$A16) -> 0 | C16: =SUMIFS(Tabela1[Amount],Tabela1[Month],Expenses!C$2,Tabela1[Category],Expenses!$A16) -> 0 | D16: =SUMIFS(Tabela1[Amount],Tabela1[Month],Expenses!D$2,Tabela1[Category],Expenses!$A16) -> 0 | E16: =SUMIFS(Tabela1[Amount],Tabela1[Month],Expenses!E$2,Tabela1[Category],Expenses!$A16) -> 0 | F16: =SUMIFS(Tabela1[Amount],Tabela1[Month],Expenses!F$2,Tabela1[Category],Expenses!$A16) -> 0 | G16: =SUMIFS(Tabela1[Amount],Tabela1[Month],Expenses!G$2,Tabela1[Category],Expenses!$A16) -> 0 | H16: =SUMIFS(Tabela1[Amount],Tabela1[Month],Expenses!H$2,Tabela1[Category],Expenses!$A16) -> 0 | I16: =SUMIFS(Tabela1[Amount],Tabela1[Month],Expenses!I$2,Tabela1[Category],Expenses!$A16) -> 0 | ... M16: =SUMIFS(Tabela1[Amount],Tabela1[Month],Expenses!M$2,Tabela1[Category],Expenses!$A16) -> 0
A17: Travel | B17: =SUMIFS(Tabela1[Amount],Tabela1[Month],Expenses!B$2,Tabela1[Category],Expenses!$A17) -> 0 | C17: =SUMIFS(Tabela1[Amount],Tabela1[Month],Expenses!C$2,Tabela1[Category],Expenses!$A17) -> 0 | D17: =SUMIFS(Tabela1[Amount],Tabela1[Month],Expenses!D$2,Tabela1[Category],Expenses!$A17) -> 0 | E17: =SUMIFS(Tabela1[Amount],Tabela1[Month],Expenses!E$2,Tabela1[Category],Expenses!$A17) -> 0 | F17: =SUMIFS(Tabela1[Amount],Tabela1[Month],Expenses!F$2,Tabela1[Category],Expenses!$A17) -> 0 | G17: =SUMIFS(Tabela1[Amount],Tabela1[Month],Expenses!G$2,Tabela1[Category],Expenses!$A17) -> 0 | H17: =SUMIFS(Tabela1[Amount],Tabela1[Month],Expenses!H$2,Tabela1[Category],Expenses!$A17) -> 0 | I17: =SUMIFS(Tabela1[Amount],Tabela1[Month],Expenses!I$2,Tabela1[Category],Expenses!$A17) -> 0 | ... M17: =SUMIFS(Tabela1[Amount],Tabela1[Month],Expenses!M$2,Tabela1[Category],Expenses!$A17) -> 0
A18: General expen. | B18: =SUMIFS(Tabela1[Amount],Tabela1[Month],Expenses!B$2,Tabela1[Category],Expenses!$A18) -> 0 | C18: =SUMIFS(Tabela1[Amount],Tabela1[Month],Expenses!C$2,Tabela1[Category],Expenses!$A18) -> 0 | D18: =SUMIFS(Tabela1[Amount],Tabela1[Month],Expenses!D$2,Tabela1[Category],Expenses!$A18) -> 0 | E18: =SUMIFS(Tabela1[Amount],Tabela1[Month],Expenses!E$2,Tabela1[Category],Expenses!$A18) -> 0 | F18: =SUMIFS(Tabela1[Amount],Tabela1[Month],Expenses!F$2,Tabela1[Category],Expenses!$A18) -> 0 | G18: =SUMIFS(Tabela1[Amount],Tabela1[Month],Expenses!G$2,Tabela1[Category],Expenses!$A18) -> 0 | H18: =SUMIFS(Tabela1[Amount],Tabela1[Month],Expenses!H$2,Tabela1[Category],Expenses!$A18) -> 0 | I18: =SUMIFS(Tabela1[Amount],Tabela1[Month],Expenses!I$2,Tabela1[Category],Expenses!$A18) -> 0 | ... M18: =SUMIFS(Tabela1[Amount],Tabela1[Month],Expenses!M$2,Tabela1[Category],Expenses!$A18) -> 0
A20: Total | B20: =SUM(B7:B18) -> 0 | C20: =SUM(C7:C18) -> 0 | D20: =SUM(D7:D18) -> 0 | E20: =SUM(E7:E18) -> 0 | F20: =SUM(F7:F18) -> 0 | G20: =SUM(G7:G18) -> 0 | H20: =SUM(H7:H18) -> 0 | I20: =SUM(I7:I18) -> 0 | ... M20: =SUM(M7:M18) -> 0

Sheet Graphic Categories
B2: Net_Salary | C2: Salary | I2: Expenses | J2: Bills
B3: Total | C3: =SUM(C6:C17) -> 0 | I3: Total | J3: =SUM(J6:J17) -> 0
B5: Month | C5: Amount | I5: Month | J5: Amount
B6: {=Months} -> January | C6: {=TRANSPOSE(_xlfn._xlws.FILTER('Net Salary'!B3:M14,Net_Salary='Graphic Categories'!C2))} -> 0 | I6: {=Months} -> January | J6: {=TRANSPOSE(_xlfn._xlws.FILTER(Expenses!B7:M18,Expenses='Graphic Categories'!J2))} -> 0
B7: February | C7: 0 | I7: February | J7: 0
B8: March | C8: 0 | I8: March | J8: 0
B9: April | C9: 0 | I9: April | J9: 0
B10: May | C10: 0 | I10: May | J10: 0
B11: June | C11: 0 | I11: June | J11: 0
B12: July | C12: 0 | I12: July | J12: 0
B13: August | C13: 0 | I13: August | J13: 0
B14: September | C14: 0 | I14: September | J14: 0
B15: October | C15: 0 | I15: October | J15: 0
B16: November | C16: 0 | I16: November | J16: 0
B17: December | C17: 0 | I17: December | J17: 0

Sheet Goals
C2: *Feel free to change the golas and their values as you wish.
D4: Goals | E4: Value | F4: Progress | H4: Account | I4: ='Balance & Tracking'!B12 -> Savings
D5: Iphone | E5: 450 | F5: =$I$5/E5 -> 0 | H5: Total | I5: ='Balance & Tracking'!C12 -> 0
D6: Console PS5 | E6: 350 | F6: =$I$5/E6 -> 0
D7: New Car | E7: 12000 | F7: =$I$5/E7 -> 0
D8: Travel | E8: 2500 | F8: =$I$5/E8 -> 0
D9: Input Goal | E9: 1 | F9: =$I$5/E9 -> 0
D10: Input Goal | E10: 1 | F10: =$I$5/E10 -> 0
D11: Input Goal | E11: 1 | F11: =$I$5/E11 -> 0
D12: Input Goal | E12: 1 | F12: =$I$5/E12 -> 0
D13: Input Goal | E13: 1 | F13: =$I$5/E13 -> 0
D14: Input Goal | E14: 1 | F14: =$I$5/E14 -> 0
D15: Input Goal | E15: 1 | F15: =$I$5/E15 -> 0
D16: Input Goal | E16: 1 | F16: =$I$5/E16 -> 0

Sheet Graphic Annual
A2: Month | C2: Net Income | D2: Investments | F2: Expenses | H2: Blc Month | I2: Blc Actual | K2: Result | N2: Fixed Expenses
A3: {=Months} -> January | C3: ='Net Salary'!B16 -> 0 | D3: =SUM('Net Salary'!B$13:B$14) -> 0 | F3: =SUM(Expenses!B20:B20) -> 0 | H3: =I3 -> 0 | I3: =Expenses!B4 -> 0 | K3: Gross Income | L3: =SUM('Net Salary'!B3:M7) -> 0 | N3: {=Expenses} -> Bills | O3: =SUM(Expenses!B7:M7) -> 0
A4: February | C4: ='Net Salary'!C16 -> 0 | D4: =SUM('Net Salary'!C$13:C$14) -> 0 | F4: =SUM(Expenses!C20:C20) -> 0 | H4: =I4-I3 -> 0 | I4: =Expenses!C4 -> 0 | K4: Discount | L4: =SUM('Net Salary'!B8:M12) -> 0 | N4: Car | O4: =SUM(Expenses!B8:M8) -> 0
A5: March | C5: ='Net Salary'!D16 -> 0 | D5: =SUM('Net Salary'!D$13:D$14) -> 0 | F5: =SUM(Expenses!D20:D20) -> 0 | H5: =I5-I4 -> 0 | I5: =Expenses!D4 -> 0 | K5: Net Income | L5: =SUM('Net Salary'!B16:M16) -> 0 | N5: Clothing | O5: =SUM(Expenses!B9:M9) -> 0
A6: April | C6: ='Net Salary'!E16 -> 0 | D6: =SUM('Net Salary'!E$13:E$14) -> 0 | F6: =SUM(Expenses!E20:E20) -> 0 | H6: =I6-I5 -> 0 | I6: =Expenses!E4 -> 0 | K6: Fixed Expen. | L6: =SUM(Expenses!B7:B17,Expenses!C7:C17,Expenses!D7:D17,Expenses!E7:E17,Expenses!F7:F17,Expenses!G7:G17,Expenses!H7:H17,Expenses!I7:I17,Expenses!J7:J17,Expenses!K7:K17,Expenses!L7:L17,Expenses!M7:M17) -> 0 | N6: Eletron n' games | O6: =SUM(Expenses!B10:M10) -> 0
A7: May | C7: ='Net Salary'!F16 -> 0 | D7: =SUM('Net Salary'!F$13:F$14) -> 0 | F7: =SUM(Expenses!F20:F20) -> 0 | H7: =I7-I6 -> 0 | I7: =Expenses!F4 -> 0 | K7: General Expen. | L7: =SUM(Expenses!B18:B18,Expenses!C18:C18,Expenses!D18:D18,Expenses!E18:E18,Expenses!F18:F18,Expenses!G18:G18,Expenses!H18:H18,Expenses!I18:I18,Expenses!J18:J18,Expenses!K18:K18,Expenses!L18:L18,Expenses!M18:M18) -> 0 | N7: Food | O7: =SUM(Expenses!B11:M11) -> 0
A8: June | C8: ='Net Salary'!G16 -> 0 | D8: =SUM('Net Salary'!G$13:G$14) -> 0 | F8: =SUM(Expenses!G20:G20) -> 0 | H8: =I8-I7 -> 0 | I8: =Expenses!G4 -> 0 | K8: Total Expen. | L8: =SUM(L6:L7) -> 0 | N8: Gasolina | O8: =SUM(Expenses!B12:M12) -> 0
A9: July | C9: ='Net Salary'!H16 -> 0 | D9: =SUM('Net Salary'!H$13:H$14) -> 0 | F9: =SUM(Expenses!H20:H20) -> 0 | H9: =I9-I8 -> 0 | I9: =Expenses!H4 -> 0 | K9: Annual Balance | L9: =Expenses!M4 -> 0 | N9: Hang out | O9: =SUM(Expenses!B13:M13) -> 0
A10: August | C10: ='Net Salary'!I16 -> 0 | D10: =SUM('Net Salary'!I$13:I$14) -> 0 | F10: =SUM(Expenses!I20:I20) -> 0 | H10: =I10-I9 -> 0 | I10: =Expenses!I4 -> 0 | K10: Investments | L10: ='Graphic Annual'!D15 -> 0 | N10: Healthcare | O10: =SUM(Expenses!B14:M14) -> 0
A11: September | C11: ='Net Salary'!J16 -> 0 | D11: =SUM('Net Salary'!J$13:J$14) -> 0 | F11: =SUM(Expenses!J20:J20) -> 0 | H11: =I11-I10 -> 0 | I11: =Expenses!J4 -> 0 | N11: Insurance | O11: =SUM(Expenses!B15:M15) -> 0
A12: October | C12: ='Net Salary'!K16 -> 0 | D12: =SUM('Net Salary'!K$13:K$14) -> 0 | F12: =SUM(Expenses!K20:K20) -> 0 | H12: =I12-I11 -> 0 | I12: =Expenses!K4 -> 0 | N12: Personal Care | O12: =SUM(Expenses!B16:M16) -> 0
A13: November | C13: ='Net Salary'!L16 -> 0 | D13: =SUM('Net Salary'!L$13:L$14) -> 0 | F13: =SUM(Expenses!L20:L20) -> 0 | H13: =I13-I12 -> 0 | I13: =Expenses!L4 -> 0 | N13: Travel | O13: =SUM(Expenses!B17:M17) -> 0
A14: December | C14: ='Net Salary'!M16 -> 0 | D14: =SUM('Net Salary'!M$13:M$14) -> 0 | F14: =SUM(Expenses!M20:N20) -> 0 | H14: =I14-I13 -> 0 | I14: =Expenses!M4 -> 0 | N14: General expen. | O14: =SUM(Expenses!B18:M18) -> 0
A15: Total | C15: =SUM(C3:C14) -> 0 | D15: =SUM(D3:D14) -> 0 | F15: =SUM(F3:F14) -> 0 | H15: Annual Balance | I15: ='Graphic Annual'!L9 -> 0
A16: Average | C16: =AVERAGE(C3:C14) -> 0 | D16: =AVERAGE(D3:D14) -> 0 | F16: =AVERAGE(F3:F14) -> 0
A17: 1º Sem. | C17: =SUM(C3:C8) -> 0 | D17: =SUM(D3:D8) -> 0 | F17: =SUM(F3:F8) -> 0
A18: 2º Sem. | C18: =SUM($C$9:$C$14) -> 0 | D18: =SUM($D$9:$D$14) -> 0 | F18: =SUM($F$9:$F$14) -> 0
